[
    {
        "Artist": "Ludwig Mies van der Rohe",
        "Title": "IIT Commons Building, Chicago, IL (Plans, elevations, sections: first floor)",
        "Year": "1953",
        "ObjectID": "290589",
        "Work": "https://www.moma.org/collection/works/290589",
        "Thumbnail": "https://www.moma.org/media/W1siZiIsIjQzOTE4NyJdLFsicCIsImNvbnZlcnQiLCItcXVhbGl0eSA5MCAtcmVzaXplIDUxMng1MTJcdTAwM2UiXV0.jpg?sha=6ec48707d39acee8",
        "Details": {
            "Medium": "Colored pencil on blueprint",
            "Dimensions": "24 x 35\" (61 x 88.9 cm)",
            "Credit": "Mies van der Rohe Archive, gift of the architect",
            "Object number": "MR5203.79",
            "Copyright": "\u00a9 2023 Artists Rights Society (ARS), New York / VG Bild-Kunst, Bonn",
            "Department": "Architecture and Design"
        },
        "Profile": "https://www.moma.org/artists/7166"
    },
    {
        "Artist": "Joan Miro",
        "Title": "Miro",
        "Year": "1953",
        "ObjectID": "7073",
        "Work": "https://www.moma.org/collection/works/7073",
        "Thumbnail": "https://www.moma.org/media/W1siZiIsIjUyMDIyMiJdLFsicCIsImNvbnZlcnQiLCItcXVhbGl0eSA5MCAtcmVzaXplIDUxMng1MTJcdTAwM2UiXV0.jpg?sha=9d1cbbc60b496616",
        "Details": {
            "Medium": "Color lithograph",
            "Dimensions": "29 3/4 x 21 15/16\" (75.6 x 55.7 cm)",
            "Credit": "Peter Stone Collection of Posters by Artists",
            "Object number": "455.1976",
            "Copyright": "\u00a9 2023 Successi\u00f3  Mir\u00f3 / Artists Rights Society (ARS), New York / ADAGP, Paris",
            "Department": "Architecture and Design"
        },
        "Profile": "https://www.moma.org/artists/4016"
    },
    {
        "Artist": "Joan Miro",
        "Title": "Maquette for poster for Recent Works (Oeuvres recentes), Galerie Maeght, Paris, 1953",
        "Year": "1953",
        "ObjectID": "37952",
        "Work": "https://www.moma.org/collection/works/37952",
        "Thumbnail": "https://www.moma.org/media/W1siZiIsIjQ0MjczMCJdLFsicCIsImNvbnZlcnQiLCItcXVhbGl0eSA5MCAtcmVzaXplIDUxMng1MTJcdTAwM2UiXV0.jpg?sha=9bb015ee9d558ea4",
        "Details": {
            "Medium": "Gouache, oil, and ink on paper",
            "Dimensions": "25 3/4 x 19 3/4\" (65.3 x 50.0 cm)",
            "Credit": "Gift in memory of Patricia Kane Matisse",
            "Object number": "744.1978",
            "Copyright": "\u00a9 2023 Successi\u00f3  Mir\u00f3 / Artists Rights Society (ARS), New York / ADAGP, Paris",
            "Department": "Drawings and Prints"
        },
        "Profile": "https://www.moma.org/artists/4016"
    },
    {
        "Artist": "Joan Miro",
        "Title": "Untitled",
        "Year": "1947, published 1952-53",
        "ObjectID": "60947",
        "Work": "https://www.moma.org/collection/works/60947",
        "Thumbnail": "https://www.moma.org/media/W1siZiIsIjIxODY0MCJdLFsicCIsImNvbnZlcnQiLCItcXVhbGl0eSA5MCAtcmVzaXplIDUxMng1MTJcdTAwM2UiXV0.jpg?sha=8545ddd31267472f",
        "Details": {
            "Medium": "Aquatint and etching",
            "Dimensions": "plate: 14 15/16 \u00d7 17 7/8\" (38 \u00d7 45.4 cm); sheet: 19 11/16 \u00d7 26\" (50 \u00d7 66 cm)",
            "Publisher": "Maeght \u00c9diteur, Paris",
            "Printer": "the artist at Atelier 17, New York and Lacouri\u00e8re, Paris",
            "Edition": "13",
            "Credit": "Gift of Abby Aldrich Rockefeller (by exchange)",
            "Object number": "51.1958",
            "Copyright": "\u00a9 2023 Successi\u00f3 Mir\u00f3 / Artists Rights Society (ARS), New York / ADAGP, Paris",
            "Department": "Drawings and Prints"
        },
        "Profile": "https://www.moma.org/artists/4016"
    },
    {
        "Artist": "Joan Miro",
        "Title": "Untitled",
        "Year": "1947, published 1952-53",
        "ObjectID": "60967",
        "Work": "https://www.moma.org/collection/works/60967",
        "Thumbnail": "https://www.moma.org/media/W1siZiIsIjIxODY1MCJdLFsicCIsImNvbnZlcnQiLCItcXVhbGl0eSA5MCAtcmVzaXplIDUxMng1MTJcdTAwM2UiXV0.jpg?sha=c11fe97237c10ee6",
        "Details": {
            "Medium": "Etching and aquatint",
            "Dimensions": "plate: 14 13/16 \u00d7 17 15/16\" (37.7 \u00d7 45.5 cm); sheet: 20 1/16 \u00d7 25 9/16\" (51 \u00d7 65 cm)",
            "Publisher": "Maeght \u00c9diteur, Paris",
            "Printer": "the artist at Atelier 17, New York and Lacouri\u00e8re, Paris",
            "Edition": "13",
            "Credit": "Gift of Abby Aldrich Rockefeller (by exchange)",
            "Object number": "52.1958",
            "Copyright": "\u00a9 2023 Successi\u00f3 Mir\u00f3 / Artists Rights Society (ARS), New York / ADAGP, Paris",
            "Department": "Drawings and Prints"
        },
        "Profile": "https://www.moma.org/artists/4016"
    },
    {
        "Artist": "Joan Miro",
        "Title": "Untitled",
        "Year": "1947, published 1952-53",
        "ObjectID": "60984",
        "Work": "https://www.moma.org/collection/works/60984",
        "Thumbnail": "https://www.moma.org/media/W1siZiIsIjQ0MjI0NCJdLFsicCIsImNvbnZlcnQiLCItcXVhbGl0eSA5MCAtcmVzaXplIDUxMng1MTJcdTAwM2UiXV0.jpg?sha=ef6875e2013e7b36",
        "Details": {
            "Medium": "Aquatint and etching",
            "Dimensions": "plate: 14 13/16 x 17 7/8\" (37.7 x 45.4 cm); sheet: 19 13/16 x 25 7/8\" (50.3 x 65.7 cm)",
            "Publisher": "Maeght \u00c9diteur, Paris",
            "Printer": "the artist at Atelier 17, New York and Lacouri\u00e8re, Paris",
            "Edition": "13",
            "Credit": "Gift of Mr. and Mrs. Walter Bareiss (by exchange)",
            "Object number": "53.1958",
            "Copyright": "\u00a9 2023 Successi\u00f3 Mir\u00f3 / Artists Rights Society (ARS), New York / ADAGP, Paris",
            "Department": "Drawings and Prints"
        },
        "Profile": "https://www.moma.org/artists/4016"
    },
    {
        "Artist": "Joan Miro",
        "Title": "Untitled",
        "Year": "1947, published 1952-53",
        "ObjectID": "67566",
        "Work": "https://www.moma.org/collection/works/67566",
        "Thumbnail": "https://www.moma.org/media/W1siZiIsIjEwMzg1NiJdLFsicCIsImNvbnZlcnQiLCItcXVhbGl0eSA5MCAtcmVzaXplIDUxMng1MTJcdTAwM2UiXV0.jpg?sha=309c7ff781db1147",
        "Details": {
            "Medium": "Etching, engraving, and aquatint",
            "Dimensions": "plate: 14 15/16 \u00d7 17 7/8\" (38 \u00d7 45.4 cm); sheet: 19 3/4 \u00d7 26\" (50.2 \u00d7 66 cm)",
            "Publisher": "Maeght \u00c9diteur, Paris",
            "Printer": "the artist at Atelier 17, New York and Lacouri\u00e8re, Paris",
            "Edition": "13",
            "Credit": "Curt Valentin Bequest",
            "Object number": "355.1955",
            "Copyright": "\u00a9 2023 Successi\u00f3  Mir\u00f3 / Artists Rights Society (ARS), New York / ADAGP, Paris",
            "Department": "Drawings and Prints"
        },
        "Profile": "https://www.moma.org/artists/4016"
    },
    {
        "Artist": "Joan Miro",
        "Title": "Untitled",
        "Year": "1947, published 1952-53",
        "ObjectID": "76984",
        "Work": "https://www.moma.org/collection/works/76984",
        "Thumbnail": "https://www.moma.org/media/W1siZiIsIjIxODMxOSJdLFsicCIsImNvbnZlcnQiLCItcXVhbGl0eSA5MCAtcmVzaXplIDUxMng1MTJcdTAwM2UiXV0.jpg?sha=9e36372d42f9a438",
        "Details": {
            "Medium": "Aquatint and etching",
            "Dimensions": "plate: 14 7/8 x 17 15/16\" (37.8 x 45.5 cm); sheet: 20 1/16 x 25 1/2\" (51 x 64.8 cm)",
            "Publisher": "Maeght \u00c9diteur, Paris",
            "Printer": "the artist at Atelier 17, New York and Lacouri\u00e8re, Paris",
            "Edition": "13",
            "Credit": "Miranda Kaiser Fund",
            "Object number": "1495.2001",
            "Copyright": "\u00a9 2023 Successi\u00f3  Mir\u00f3 / Artists Rights Society (ARS), New York / ADAGP, Paris",
            "Department": "Drawings and Prints"
        },
        "Profile": "https://www.moma.org/artists/4016"
    },
    {
        "Artist": "Joan Miro",
        "Title": "Untitled",
        "Year": "1947, published 1952-53",
        "ObjectID": "76987",
        "Work": "https://www.moma.org/collection/works/76987",
        "Thumbnail": "https://www.moma.org/media/W1siZiIsIjUzMDM0MCJdLFsicCIsImNvbnZlcnQiLCItcXVhbGl0eSA5MCAtcmVzaXplIDUxMng1MTJcdTAwM2UiXV0.jpg?sha=62652ecef2e1fcfe",
        "Details": {
            "Medium": "Etching and aquatint",
            "Dimensions": "plate: 14 13/16 \u00d7 17 15/16\" (37.7 \u00d7 45.5 cm); sheet: 19 11/16 \u00d7 21 15/16\" (50 \u00d7 55.8 cm)",
            "Publisher": "Maeght \u00c9diteur, Paris",
            "Printer": "the artist at Atelier 17, New York and Lacouri\u00e8re, Paris",
            "Edition": "13",
            "Credit": "The Associates Fund",
            "Object number": "1496.2001",
            "Copyright": "\u00a9 2023 Successi\u00f3  Mir\u00f3 / Artists Rights Society (ARS), New York / ADAGP, Paris",
            "Department": "Drawings and Prints"
        },
        "Profile": "https://www.moma.org/artists/4016"
    },
    {
        "Artist": "Lisette Model",
        "Title": "In front of La Comedie Francaise, Paris",
        "Year": "1953",
        "ObjectID": "57223",
        "Work": "https://www.moma.org/collection/works/57223",
        "Thumbnail": "https://www.moma.org/media/W1siZiIsIjIwMTI5OCJdLFsicCIsImNvbnZlcnQiLCItcXVhbGl0eSA5MCAtcmVzaXplIDUxMng1MTJcdTAwM2UiXV0.jpg?sha=f3ffe63b7408ddad",
        "Details": {
            "Medium": "Gelatin silver print",
            "Dimensions": "15 15/16 \u00d7 19 7/8\" (40.5 \u00d7 50.5 cm)",
            "Credit": "Gift of the artist",
            "Object number": "875.1965",
            "Copyright": "\u00a9 2023 Estate of Lisette Model, courtesy Baudoin Lebon Gallery, Paris and Keitelman Gallery, Brussels",
            "Department": "Photography"
        },
        "Profile": "https://www.moma.org/artists/4036"
    },
    {
        "Artist": "Lisette Model",
        "Title": "Sculpture, Museo Romano",
        "Year": "1953",
        "ObjectID": "57227",
        "Work": "https://www.moma.org/collection/works/57227",
        "Thumbnail": "https://www.moma.org/media/W1siZiIsIjIwMTMwMCJdLFsicCIsImNvbnZlcnQiLCItcXVhbGl0eSA5MCAtcmVzaXplIDUxMng1MTJcdTAwM2UiXV0.jpg?sha=f09aa520e902bf78",
        "Details": {
            "Medium": "Gelatin silver print",
            "Dimensions": "19 7/8 \u00d7 15 15/16\" (50.5 \u00d7 40.6 cm)",
            "Credit": "Gift of the artist",
            "Object number": "876.1965",
            "Copyright": "\u00a9 2023 Estate of Lisette Model, courtesy Baudoin Lebon Gallery, Paris and Keitelman Gallery, Brussels",
            "Department": "Photography"
        },
        "Profile": "https://www.moma.org/artists/4036"
    },
    {
        "Artist": "Piet Mondrian",
        "Title": "Composition from Art of Today, Masters of Abstract Art (Art d'aujourd'hui, maitres de l'art abstrait), Album I",
        "Year": "1953 (original executed in 1921)",
        "ObjectID": "31863",
        "Work": "https://www.moma.org/collection/works/31863",
        "Thumbnail": "https://www.moma.org/media/W1siZiIsIjMzNzE4MCJdLFsicCIsImNvbnZlcnQiLCItcXVhbGl0eSA5MCAtcmVzaXplIDUxMng1MTJcdTAwM2UiXV0.jpg?sha=5774ea039a6c7cdf",
        "Details": {
            "Medium": "One from a portfolio of sixteen screenprint reproductions",
            "Dimensions": "composition: 12 5/16 \u00d7 12 1/4\" (31.3 \u00d7 31.1 cm); sheet: 25 3/16 \u00d7 19 5/16\" (63.9 \u00d7 49 cm)",
            "Publisher": "\u00c9dition Art d'Aujourd'hui, Boulogne",
            "Printer": "\u00c9dition Art d'Aujourd'hui, Boulogne",
            "Edition": "300",
            "Credit": "The Louis E. Stern Collection",
            "Object number": "1106.1964.12",
            "Portfolio": "Art of Today, Masters of Abstract Art (Art d'aujourd'hui, ma\u00eetres de l'art abstrait), Album I",
            "Department": "Drawings and Prints"
        },
        "Profile": "https://www.moma.org/artists/4057"
    },
    {
        "Artist": "Henry Moore",
        "Title": "Study for sculpture on Time-Life Building, London",
        "Year": "1952-53",
        "ObjectID": "80835",
        "Work": "https://www.moma.org/collection/works/80835",
        "Thumbnail": null,
        "Details": {
            "Medium": "Bronze",
            "Dimensions": "15 x 38 7/8 x 2 7/8\" (38.1 x 98.7 x 7.3 cm)",
            "Credit": "Gift of Time, Inc.",
            "Object number": "18.1954",
            "Department": "Painting and Sculpture"
        },
        "Profile": "https://www.moma.org/artists/4071"
    },
    {
        "Artist": "Inge Morath",
        "Title": "Mrs. Eveleigh Nash with her Chauffeur at Buckingham Palace Mall",
        "Year": "1953",
        "ObjectID": "139202",
        "Work": "https://www.moma.org/collection/works/139202",
        "Thumbnail": "https://www.moma.org/media/W1siZiIsIjIwMjAzOCJdLFsicCIsImNvbnZlcnQiLCItcXVhbGl0eSA5MCAtcmVzaXplIDUxMng1MTJcdTAwM2UiXV0.jpg?sha=917dd9780f07b29d",
        "Details": {
            "Medium": "Gelatin silver print",
            "Dimensions": "8 1/4 \u00d7 11 3/4\" (21 \u00d7 29.8 cm)",
            "Credit": "The Family of Man Fund",
            "Object number": "602.2010",
            "Copyright": "\u00a9 The Inge Morath Foundation/Magnum Photos",
            "Department": "Photography"
        },
        "Profile": "https://www.moma.org/artists/38512"
    },
    {
        "Artist": "Josef Muller-Brockmann",
        "Title": "5. Fruhjahrskonzert der Tonhalle-Gesellschaft (5th Spring concert of the Acoustic Society)",
        "Year": "1953",
        "ObjectID": "6313",
        "Work": "https://www.moma.org/collection/works/6313",
        "Thumbnail": "https://www.moma.org/media/W1siZiIsIjUxNzk3MCJdLFsicCIsImNvbnZlcnQiLCItcXVhbGl0eSA5MCAtcmVzaXplIDUxMng1MTJcdTAwM2UiXV0.jpg?sha=235355e4aa043b4e",
        "Details": {
            "Medium": "Lithograph",
            "Dimensions": "39 x 27 3/4\" (99.5 x 70.5 cm)",
            "Credit": "Gift of the Kunstgewerbe Museum, Z\u00fcrich",
            "Object number": "332.1957",
            "Department": "Architecture and Design"
        },
        "Profile": "https://www.moma.org/artists/4154"
    },
    {
        "Artist": "Robert Emmett Muller",
        "Title": "Flutist",
        "Year": "1953",
        "ObjectID": "62470",
        "Work": "https://www.moma.org/collection/works/62470",
        "Thumbnail": "https://www.moma.org/media/W1siZiIsIjIxODI5MiJdLFsicCIsImNvbnZlcnQiLCItcXVhbGl0eSA5MCAtcmVzaXplIDUxMng1MTJcdTAwM2UiXV0.jpg?sha=0b7c33048ae7bf98",
        "Details": {
            "Medium": "Woodcut",
            "Dimensions": "composition: 7 7/16 x 20 3/8\" (18.9 x 51.7cm); sheet: 11 3/4 x 24\" (29.8 x 61cm)",
            "Credit": "Gift of the Junior Council",
            "Object number": "132.1954",
            "Department": "Drawings and Prints"
        },
        "Profile": "https://www.moma.org/artists/4141"
    },
    {
        "Artist": "Bruno Munari",
        "Title": "Pirelli, Suola Coria",
        "Year": "1953",
        "ObjectID": "5721",
        "Work": "https://www.moma.org/collection/works/5721",
        "Thumbnail": null,
        "Details": {
            "Medium": "Offset lithograph",
            "Dimensions": "38 x 27\" (96.5 x 68.5 cm)",
            "Printer": "A. Pizzi S.A., Milan",
            "Credit": "Gift of Pirelli Company, Milan",
            "Object number": "217.1956",
            "Department": "Architecture and Design"
        },
        "Profile": "https://www.moma.org/artists/4163"
    },
    {
        "Artist": "Bruno Munari",
        "Title": "Pirelli, Suola Coria",
        "Year": "1953",
        "ObjectID": "7406",
        "Work": "https://www.moma.org/collection/works/7406",
        "Thumbnail": "https://www.moma.org/media/W1siZiIsIjIyMTY4NyJdLFsicCIsImNvbnZlcnQiLCItcXVhbGl0eSA5MCAtcmVzaXplIDUxMng1MTJcdTAwM2UiXV0.jpg?sha=142314891d1469fb",
        "Details": {
            "Medium": "Offset lithograph",
            "Dimensions": "54 1/4 x 38 1/2\" (137.8 x 97.8 cm)",
            "Printer": "A. Pizzi S.A., Milan",
            "Credit": "Gift of the designer",
            "Object number": "527.1954",
            "Department": "Architecture and Design"
        },
        "Profile": "https://www.moma.org/artists/4163"
    },
    {
        "Artist": "Zoran Music",
        "Title": "Dalmatian Theme",
        "Year": "1953",
        "ObjectID": "62487",
        "Work": "https://www.moma.org/collection/works/62487",
        "Thumbnail": "https://www.moma.org/media/W1siZiIsIjE2NzQ3NyJdLFsicCIsImNvbnZlcnQiLCItcXVhbGl0eSA5MCAtcmVzaXplIDUxMng1MTJcdTAwM2UiXV0.jpg?sha=eff428b03c762a12",
        "Details": {
            "Medium": "Lithograph",
            "Dimensions": "composition: 9 5/8 x 12 5/8\" (24.5 x 32cm); sheet (folded): 9 7/8 x 13\" (25.1 x 33cm)",
            "Credit": "Gift of Allen Porter",
            "Object number": "133.1954",
            "Department": "Drawings and Prints"
        },
        "Profile": "https://www.moma.org/artists/4189"
    },
    {
        "Artist": "Zoran Music",
        "Title": "Colts (Cavallini)",
        "Year": "1953",
        "ObjectID": "62516",
        "Work": "https://www.moma.org/collection/works/62516",
        "Thumbnail": "https://www.moma.org/media/W1siZiIsIjE2NzQ3OCJdLFsicCIsImNvbnZlcnQiLCItcXVhbGl0eSA5MCAtcmVzaXplIDUxMng1MTJcdTAwM2UiXV0.jpg?sha=51a69a03664f24f1",
        "Details": {
            "Medium": "Lithograph",
            "Dimensions": "composition: 12 7/8 x 17\" (32.7 x 43.2cm); sheet: 15 1/4 x 19 9/16\" (38.7 x 49.7cm)",
            "Printer": "Emil Matthieu Zurich",
            "Edition": "200",
            "Credit": "Larry Aldrich Fund",
            "Object number": "134.1954",
            "Department": "Drawings and Prints"
        },
        "Profile": "https://www.moma.org/artists/4189"
    },
    {
        "Artist": "Alice Neel",
        "Title": "Georgie Arce",
        "Year": "1953",
        "ObjectID": "222282",
        "Work": "https://www.moma.org/collection/works/222282",
        "Thumbnail": "https://www.moma.org/media/W1siZiIsIjQwMDg4NyJdLFsicCIsImNvbnZlcnQiLCItcXVhbGl0eSA5MCAtcmVzaXplIDUxMng1MTJcdTAwM2UiXV0.jpg?sha=493fda7e270f859a",
        "Details": {
            "Medium": "Oil on canvas",
            "Dimensions": "38 \u00d7 28\" (96.5 \u00d7 71.1 cm)",
            "Credit": "Promised gift of Glenn and Eva Dubin",
            "Object number": "PG502.2017",
            "Department": "Painting and Sculpture"
        },
        "Profile": "https://www.moma.org/artists/4253"
    },
    {
        "Artist": "Hannes Neuner",
        "Title": "Grafik Fotografie Fotografik, Amerika-Haus Munchen",
        "Year": "1953",
        "ObjectID": "4888",
        "Work": "https://www.moma.org/collection/works/4888",
        "Thumbnail": null,
        "Details": {
            "Medium": "Photolithograph",
            "Dimensions": "21 x 36 3/8\" (53.3 x 92.4 cm)",
            "Credit": "Gift of Amerika Haus",
            "Object number": "59.1960",
            "Department": "Architecture and Design"
        },
        "Profile": "https://www.moma.org/artists/4275"
    },
    {
        "Artist": "Arnold Newman",
        "Title": "Ibram Lassaw",
        "Year": "1953",
        "ObjectID": "54350",
        "Work": "https://www.moma.org/collection/works/54350",
        "Thumbnail": "https://www.moma.org/media/W1siZiIsIjE5MDM3MyJdLFsicCIsImNvbnZlcnQiLCItcXVhbGl0eSA5MCAtcmVzaXplIDUxMng1MTJcdTAwM2UiXV0.jpg?sha=d1ff6a387c34cb12",
        "Details": {
            "Medium": "Gelatin silver print",
            "Dimensions": "9 1/2 \u00d7 7 5/8\" (24.1 \u00d7 19.4 cm)",
            "Credit": "Gift of the artist",
            "Object number": "494.1959",
            "Department": "Photography"
        },
        "Profile": "https://www.moma.org/artists/4284"
    },
    {
        "Artist": "Billie Newmarch",
        "Title": "Beach Seats",
        "Year": "1953",
        "ObjectID": "2575",
        "Work": "https://www.moma.org/collection/works/2575",
        "Thumbnail": "https://www.moma.org/media/W1siZiIsIjIyODQxNyJdLFsicCIsImNvbnZlcnQiLCItcXVhbGl0eSA5MCAtcmVzaXplIDUxMng1MTJcdTAwM2UiXV0.jpg?sha=b801ea5c48745018",
        "Details": {
            "Manufacturer": "Billie Newmarch",
            "Medium": "Legless tubular metal frames and colored cotton slip covers",
            "Credit": "Gift of the designer",
            "Object number": "152.1958.1-3",
            "Department": "Architecture and Design"
        },
        "Profile": "https://www.moma.org/artists/4287"
    },
    {
        "Artist": "Oscar Niemeyer, Wallace K. Harrison, United Nations Headquarters Board of Design",
        "Title": "Proposal for United Nations Headquarters (Scheme 32), New York, New York (Perspective, plan, and axonometric)",
        "Year": "1947",
        "ObjectID": "69",
        "Work": "https://www.moma.org/collection/works/69",
        "Thumbnail": "https://www.moma.org/media/W1siZiIsIjM3NiJdLFsicCIsImNvbnZlcnQiLCItcXVhbGl0eSA5MCAtcmVzaXplIDUxMng1MTJcdTAwM2UiXV0.jpg?sha=41b69d58aa55dacc",
        "Details": {
            "Medium": "Ink on tracing paper",
            "Dimensions": "19 1/2 x 37 3/4\" (49.5 x 95.9 cm)",
            "Credit": "Gift of Hester Diamond",
            "Object number": "SC10.1988",
            "Department": "Architecture and Design"
        },
        "Profile": "https://www.moma.org/artists/8103"
    },
    {
        "Artist": "Oscar Niemeyer, Wallace K. Harrison, United Nations Headquarters Board of Design, United Nations Headquarters Board of Design, Wallace K. Harrison",
        "Title": "Proposal for United Nations Headquarters (scheme 32), New York, New York, Plot plan",
        "Year": "1947",
        "ObjectID": "77",
        "Work": "https://www.moma.org/collection/works/77",
        "Thumbnail": null,
        "Details": {
            "Collaborating artist": "United Nations Headquarters Board of Design, Wallace K. Harrison",
            "Medium": "Graphite on tracing paper",
            "Dimensions": "19 5/8 x 37 3/4\" (50 x 96 cm)",
            "Credit": "Gift of Hester Diamond",
            "Object number": "SC17.1988",
            "Department": "Architecture and Design"
        },
        "Profile": "https://www.moma.org/artists/8103"
    },
    {
        "Artist": "Costantino Nivola",
        "Title": "A71 (Study for the Olivetti Showroom, New York, NY)",
        "Year": "1953",
        "ObjectID": "446105",
        "Work": "https://www.moma.org/collection/works/446105",
        "Thumbnail": null,
        "Details": {
            "Medium": "Sandcast plaster with pigment",
            "Dimensions": "30 5/8 \u00d7 49 7/8 \u00d7 3 3/4\" (77.8 \u00d7 126.7 \u00d7 9.5 cm), 85 lbs",
            "Credit": "Promised gift of  Alice and Tom Tisch",
            "Object number": "PG74.2023",
            "Department": "Architecture and Design"
        },
        "Profile": "https://www.moma.org/artists/4314"
    },
    {
        "Artist": "Ruben Nunez",
        "Title": "Kinetic Experiment",
        "Year": "1953",
        "ObjectID": "205968",
        "Work": "https://www.moma.org/collection/works/205968",
        "Thumbnail": "https://www.moma.org/media/W1siZiIsIjQ0NjA4NSJdLFsicCIsImNvbnZlcnQiLCItcXVhbGl0eSA5MCAtcmVzaXplIDUxMng1MTJcdTAwM2UiXV0.jpg?sha=1658a7bcbe931792",
        "Details": {
            "Medium": "Wire and gouache on paper over wood",
            "Dimensions": "8 1/16 \u00d7 10 5/8\" (20.5 \u00d7 27 cm)",
            "Credit": "Gift of Patricia Phelps de Cisneros through the Latin American and Caribbean Fund in honor of Samuel Guill\u00e9n",
            "Object number": "839.2016",
            "Department": "Painting and Sculpture"
        },
        "Profile": "https://www.moma.org/artists/50005"
    },
    {
        "Artist": "Victor Obsatz",
        "Title": "Marcel Duchamp",
        "Year": "1953",
        "ObjectID": "429653",
        "Work": "https://www.moma.org/collection/works/429653",
        "Thumbnail": "https://www.moma.org/media/W1siZiIsIjUxMzgzNSJdLFsicCIsImNvbnZlcnQiLCItcXVhbGl0eSA5MCAtcmVzaXplIDUxMng1MTJcdTAwM2UiXV0.jpg?sha=c776d8d6f4c13390",
        "Details": {
            "Medium": "Gelatin silver print",
            "Dimensions": "13 1/2 \u00d7 10 1/2\" (34.3 \u00d7 26.7 cm)",
            "Credit": "Gift of Arthur and Susan Fleischer",
            "Object number": "564.2021",
            "Copyright": "\u00a9 2023 Victor Obsatz",
            "Department": "Photography"
        },
        "Profile": "https://www.moma.org/artists/134330"
    },
    {
        "Artist": "Richard Oelze",
        "Title": "Performer",
        "Year": "1952-53",
        "ObjectID": "33206",
        "Work": "https://www.moma.org/collection/works/33206",
        "Thumbnail": "https://www.moma.org/media/W1siZiIsIjMxODAxMCJdLFsicCIsImNvbnZlcnQiLCItcXVhbGl0eSA5MCAtcmVzaXplIDUxMng1MTJcdTAwM2UiXV0.jpg?sha=60a580a0e9051836",
        "Details": {
            "Medium": "Crayon on black paper",
            "Dimensions": "19 3/8 x 25 1/2\" (49.2 x 64.8 cm)",
            "Credit": "Gertrud A. Mellon Fund",
            "Object number": "16.1962",
            "Department": "Drawings and Prints"
        },
        "Profile": "https://www.moma.org/artists/4376"
    },
    {
        "Artist": "Kenzo Okada",
        "Title": "Number 3",
        "Year": "1953",
        "ObjectID": "79271",
        "Work": "https://www.moma.org/collection/works/79271",
        "Thumbnail": "https://www.moma.org/media/W1siZiIsIjE3MTQwMSJdLFsicCIsImNvbnZlcnQiLCItcXVhbGl0eSA5MCAtcmVzaXplIDUxMng1MTJcdTAwM2UiXV0.jpg?sha=5c27ee5b53400dca",
        "Details": {
            "Medium": "Oil on canvas",
            "Dimensions": "65 1/8 x 57 7/8\" (165.4 x 147 cm)",
            "Credit": "Given anonymously",
            "Object number": "248.1954",
            "Department": "Painting and Sculpture"
        },
        "Profile": "https://www.moma.org/artists/7902"
    },
    {
        "Artist": "Toshiko Okanoue",
        "Title": "In Love",
        "Year": "1953",
        "ObjectID": "126250",
        "Work": "https://www.moma.org/collection/works/126250",
        "Thumbnail": "https://www.moma.org/media/W1siZiIsIjI0MDc1MSJdLFsicCIsImNvbnZlcnQiLCItcXVhbGl0eSA5MCAtcmVzaXplIDUxMng1MTJcdTAwM2UiXV0.jpg?sha=4d8d34077815567c",
        "Details": {
            "Medium": "Cut-and-pasted printed papers on printed paper",
            "Dimensions": "14 x 9 5/8\" (35.6 x 24.4 cm)",
            "Credit": "Committee on Photography Fund and Committee on Drawings Funds",
            "Object number": "280.2009",
            "Copyright": "\u00a9 2023 Toshiko Okanoue",
            "Department": "Drawings and Prints"
        },
        "Profile": "https://www.moma.org/artists/36607"
    },
    {
        "Artist": "Lennart Olson",
        "Title": "Skanstullsbron III, Stockholm",
        "Year": "1953",
        "ObjectID": "50246",
        "Work": "https://www.moma.org/collection/works/50246",
        "Thumbnail": "https://www.moma.org/media/W1siZiIsIjIwMTA5MSJdLFsicCIsImNvbnZlcnQiLCItcXVhbGl0eSA5MCAtcmVzaXplIDUxMng1MTJcdTAwM2UiXV0.jpg?sha=e98fd116562f7d5e",
        "Details": {
            "Medium": "Gelatin silver print",
            "Dimensions": "10 3/8 \u00d7 15 3/8\" (26.5 \u00d7 39.1 cm)",
            "Credit": "Gift of the artist",
            "Object number": "302.1959",
            "Copyright": "\u00a9 2023 Lennart Olson",
            "Department": "Photography"
        },
        "Profile": "https://www.moma.org/artists/4406"
    },
    {
        "Artist": "Harold Osrow",
        "Title": "Quik-Suds Semi-Automatic Dishwasher",
        "Year": "c. 1948",
        "ObjectID": "137486",
        "Work": "https://www.moma.org/collection/works/137486",
        "Thumbnail": "https://www.moma.org/media/W1siZiIsIjI3OTIxOSJdLFsicCIsImNvbnZlcnQiLCItcXVhbGl0eSA5MCAtcmVzaXplIDUxMng1MTJcdTAwM2UiXV0.jpg?sha=738449de7a220b2e",
        "Details": {
            "Manufacturer": "Osrow Products Co. Inc., Queens Village, NY",
            "Medium": "Plastic, rubber, nylon and steel",
            "Dimensions": "Box: 7 x 14 x 20\" (17.8 x 35.6 x 50.8 cm)",
            "Credit": "Gift of Adriaan van Ravesteijn",
            "Object number": "SC573.2010",
            "Department": "Architecture and Design"
        },
        "Profile": "https://www.moma.org/artists/38578"
    },
    {
        "Artist": "Roberto Ossaye",
        "Title": "Dragon Fruit",
        "Year": "1953",
        "ObjectID": "78466",
        "Work": "https://www.moma.org/collection/works/78466",
        "Thumbnail": "https://www.moma.org/media/W1siZiIsIjIwODAxNyJdLFsicCIsImNvbnZlcnQiLCItcXVhbGl0eSA5MCAtcmVzaXplIDUxMng1MTJcdTAwM2UiXV0.jpg?sha=165f1e7af55f045f",
        "Details": {
            "Medium": "Oil on canvas",
            "Dimensions": "12 7/8 x 18 3/4\" (32.7 x 47.5 cm)",
            "Credit": "Given in memory of the artist by Mrs. Roberto Ossaye and her daughter, Maria del Carmen Ossaye",
            "Object number": "17.1957",
            "Department": "Painting and Sculpture"
        },
        "Profile": "https://www.moma.org/artists/4440"
    },
    {
        "Artist": "Gen Otsuka",
        "Title": "Snow Fantasy",
        "Year": "1953",
        "ObjectID": "49172",
        "Work": "https://www.moma.org/collection/works/49172",
        "Thumbnail": "https://www.moma.org/media/W1siZiIsIjE1OTQ0MyJdLFsicCIsImNvbnZlcnQiLCItcXVhbGl0eSA5MCAtcmVzaXplIDUxMng1MTJcdTAwM2UiXV0.jpg?sha=9109620fdb72e4e3",
        "Details": {
            "Medium": "Gelatin silver print",
            "Dimensions": "10 7/8 \u00d7 14\" (27.5 \u00d7 35.4 cm)",
            "Credit": "Gift of Nihon Keizai Shimbun",
            "Object number": "229.1959",
            "Copyright": "\u00a9 2023 Gen Otsuka",
            "Department": "Photography"
        },
        "Profile": "https://www.moma.org/artists/74302"
    },
    {
        "Artist": "Paul Outerbridge",
        "Title": "Abstract Form",
        "Year": "1911",
        "ObjectID": "65704",
        "Work": "https://www.moma.org/collection/works/65704",
        "Thumbnail": "https://www.moma.org/media/W1siZiIsIjE2NzUxOCJdLFsicCIsImNvbnZlcnQiLCItcXVhbGl0eSA5MCAtcmVzaXplIDUxMng1MTJcdTAwM2UiXV0.jpg?sha=c4887548befaa96f",
        "Details": {
            "Medium": "Etching",
            "Dimensions": "plate: 13 3/4 x 9 7/16\" (34.9 x 23.9cm); sheet: 16 15/16 x 12 1/2\" (43.1 x 31.7cm)",
            "Credit": "Katherine S. Dreier Bequest",
            "Object number": "270.1953",
            "Department": "Drawings and Prints"
        },
        "Profile": "https://www.moma.org/artists/4452"
    },
    {
        "Artist": "Yasujiro Ozu",
        "Title": "Tokyo monogatari (Tokyo Story)",
        "Year": "1953",
        "ObjectID": "300675",
        "Work": "https://www.moma.org/collection/works/300675",
        "Thumbnail": "https://www.moma.org/media/W1siZiIsIjczOTU3Il0sWyJwIiwiY29udmVydCIsIi1xdWFsaXR5IDkwIC1yZXNpemUgNTEyeDUxMlx1MDAzZSJdXQ.jpg?sha=9d5de4a229dd7286",
        "Details": {
            "Producer": "Takeshi Yamamoto",
            "Object number": "W2053",
            "Department": "Film"
        },
        "Profile": "https://www.moma.org/artists/77749"
    },
    {
        "Artist": "Gordon Parks",
        "Title": "Arrested, Metropolitan Baptist Church, Chicago",
        "Year": "1953",
        "ObjectID": "146484",
        "Work": "https://www.moma.org/collection/works/146484",
        "Thumbnail": "https://www.moma.org/media/W1siZiIsIjIxODYxMCJdLFsicCIsImNvbnZlcnQiLCItcXVhbGl0eSA5MCAtcmVzaXplIDUxMng1MTJcdTAwM2UiXV0.jpg?sha=67fe06593639e791",
        "Details": {
            "Medium": "Gelatin silver print",
            "Dimensions": "13 9/16 \u00d7 10 1/2\" (34.4 \u00d7 26.7 cm)",
            "Credit": "David H. McAlpin Fund",
            "Object number": "452.2011",
            "Copyright": "\u00a9 2023 Gordon Parks Foundation",
            "Department": "Photography"
        },
        "Profile": "https://www.moma.org/artists/8083"
    },
    {
        "Artist": "Victor Pasmore",
        "Title": "Square Motif in Brown, White, Black, Blue, and Ochre",
        "Year": "1948/53",
        "ObjectID": "80608",
        "Work": "https://www.moma.org/collection/works/80608",
        "Thumbnail": "https://www.moma.org/media/W1siZiIsIjIwOTU4NCJdLFsicCIsImNvbnZlcnQiLCItcXVhbGl0eSA5MCAtcmVzaXplIDUxMng1MTJcdTAwM2UiXV0.jpg?sha=65fa2dbf2a9da4e2",
        "Details": {
            "Medium": "Paper collage and oil on canvas",
            "Dimensions": "25 x 30\" (63.5 x 76.1 cm)",
            "Credit": "Gift of Mr. and Mrs. Allan D. Emil",
            "Object number": "1241.1964",
            "Department": "Painting and Sculpture"
        },
        "Profile": "https://www.moma.org/artists/4515"
    },
    {
        "Artist": "Francis Picabia",
        "Title": "A Little Solitude in the Midst of Suns (Petite solitude au milieu des soleils) from Art of Today, Masters of Abstract Art (Art d'aujourd'hui, maitres de l'art abstrait), Album I",
        "Year": "1953 (original executed in 1915)",
        "ObjectID": "31864",
        "Work": "https://www.moma.org/collection/works/31864",
        "Thumbnail": "https://www.moma.org/media/W1siZiIsIjMzNzE4MSJdLFsicCIsImNvbnZlcnQiLCItcXVhbGl0eSA5MCAtcmVzaXplIDUxMng1MTJcdTAwM2UiXV0.jpg?sha=d1856d513d72328d",
        "Details": {
            "Medium": "One from a portfolio of sixteen screenprint reproductions",
            "Dimensions": "composition: 19 1/2 \u00d7 14\" (49.5 \u00d7 35.6 cm); sheet: 25 3/16 \u00d7 19 1/4\" (64 \u00d7 48.9 cm)",
            "Publisher": "\u00c9dition Art d'Aujourd'hui, Boulogne",
            "Printer": "\u00c9dition Art d'Aujourd'hui, Boulogne",
            "Edition": "300",
            "Credit": "The Louis E. Stern Collection",
            "Object number": "1106.1964.13",
            "Copyright": "\u00a9 2023 Artists Rights Society (ARS), New York / ADAGP, Paris",
            "Portfolio": "Art of Today, Masters of Abstract Art (Art d'aujourd'hui, ma\u00eetres de l'art abstrait), Album I",
            "Department": "Drawings and Prints"
        },
        "Profile": "https://www.moma.org/artists/4607"
    },
    {
        "Artist": "Pablo Picasso",
        "Title": "Six Contes Fantastiques",
        "Year": "1953.  (Prints executed 1944).",
        "ObjectID": "29884",
        "Work": "https://www.moma.org/collection/works/29884",
        "Thumbnail": "https://www.moma.org/media/W1siZiIsIjE3MzY0MSJdLFsicCIsImNvbnZlcnQiLCItcXVhbGl0eSA5MCAtcmVzaXplIDUxMng1MTJcdTAwM2UiXV0.jpg?sha=9521ee8784c87c65",
        "Details": {
            "Author": "Maurice Toesca",
            "Medium": "Illustrated book with 6 engravings; and 5 wood engraved ornamental initials by Pierre Bouchet; and added portfolio edition of 6 engravings",
            "Dimensions": "page (book): 13 3/16 x 10\" (33.5 x 25.5 cm); sheet (portfolio, irreg.):  15 3/4 x 12 5/16\" (40.0 x 31.3 cm); prints:  various dimensions.",
            "Publisher": "Flammarion, Paris",
            "Printer": "Lacouri\u00e8re, Paris",
            "Edition": "Book: 225 (25 numbered 1-25 on old Japan with supplementary suite; 75 numbered 26-100 on Montval; 100 numbered 101-200 on Arches; 25 numbered I-XXV). Portfolio: 30 (numbered 1/30-30/30 reserved for friends of the publisher)",
            "Credit": "The Louis E. Stern Collection",
            "Object number": "1002.1964.A-B",
            "Copyright": "\u00a9 2023 Estate of Pablo Picasso / Artists Rights Society (ARS), New York",
            "Department": "Drawings and Prints"
        },
        "Profile": "https://www.moma.org/artists/4609"
    },
    {
        "Artist": "Pablo Picasso",
        "Title": "Profile and Female Nude (plate, page 5) from the illustrated book Six Contes Fantastiques",
        "Year": "1944-1953",
        "ObjectID": "29885",
        "Work": "https://www.moma.org/collection/works/29885",
        "Thumbnail": "https://www.moma.org/media/W1siZiIsIjE3MzY0NiJdLFsicCIsImNvbnZlcnQiLCItcXVhbGl0eSA5MCAtcmVzaXplIDUxMng1MTJcdTAwM2UiXV0.jpg?sha=69d6d937c542cefc",
        "Details": {
            "Medium": "Engraving",
            "Dimensions": "composition (irreg.): 12 13/16 x 9 13/16\" (32.5 x 24.9 cm); page: 13 3/16 x 10 1/16\" (33.5 x 25.5 cm)",
            "Credit": "The Louis E. Stern Collection",
            "Object number": "1002.1964.A1",
            "Copyright": "\u00a9 2023 Estate of Pablo Picasso / Artists Rights Society (ARS), New York",
            "Department": "Drawings and Prints"
        },
        "Profile": "https://www.moma.org/artists/4609"
    },
    {
        "Artist": "Pablo Picasso",
        "Title": "Nude with Necklace from the illustrated book Six Contes Fantastiques",
        "Year": "1944-1953",
        "ObjectID": "29886",
        "Work": "https://www.moma.org/collection/works/29886",
        "Thumbnail": "https://www.moma.org/media/W1siZiIsIjE3MzY0NyJdLFsicCIsImNvbnZlcnQiLCItcXVhbGl0eSA5MCAtcmVzaXplIDUxMng1MTJcdTAwM2UiXV0.jpg?sha=4de8c2915736df56",
        "Details": {
            "Medium": "Engraving",
            "Dimensions": "composition (irreg.): 12 11/16 x 8 7/8\" (32.3 x 22.6 cm); page: 13 3/16 x 10 1/16\" (33.5 x 25.5 cm)",
            "Credit": "The Louis E. Stern Collection",
            "Object number": "1002.1964.A2",
            "Copyright": "\u00a9 2023 Estate of Pablo Picasso / Artists Rights Society (ARS), New York",
            "Department": "Drawings and Prints"
        },
        "Profile": "https://www.moma.org/artists/4609"
    },
    {
        "Artist": "Pablo Picasso",
        "Title": "Profile of Woman from the illustrated book Six Contes Fantastiques",
        "Year": "1944-1953",
        "ObjectID": "29887",
        "Work": "https://www.moma.org/collection/works/29887",
        "Thumbnail": "https://www.moma.org/media/W1siZiIsIjE3MzY0OCJdLFsicCIsImNvbnZlcnQiLCItcXVhbGl0eSA5MCAtcmVzaXplIDUxMng1MTJcdTAwM2UiXV0.jpg?sha=77cfaacbf9dc8a5f",
        "Details": {
            "Medium": "Engraving",
            "Dimensions": "composition (irreg.): 13 x 7 7/8\" (33 x 20 cm); page: 13 3/16 x 10 1/16\" (33.5 x 25.5 cm)",
            "Credit": "The Louis E. Stern Collection",
            "Object number": "1002.1964.A3",
            "Copyright": "\u00a9 2023 Estate of Pablo Picasso / Artists Rights Society (ARS), New York",
            "Department": "Drawings and Prints"
        },
        "Profile": "https://www.moma.org/artists/4609"
    },
    {
        "Artist": "Pablo Picasso",
        "Title": "Sculpture from the illustrated book Six Contes Fantastiques",
        "Year": "1944-1953",
        "ObjectID": "29888",
        "Work": "https://www.moma.org/collection/works/29888",
        "Thumbnail": "https://www.moma.org/media/W1siZiIsIjE3MzY0OSJdLFsicCIsImNvbnZlcnQiLCItcXVhbGl0eSA5MCAtcmVzaXplIDUxMng1MTJcdTAwM2UiXV0.jpg?sha=cf3d2f0c52e6dee9",
        "Details": {
            "Medium": "Engraving",
            "Dimensions": "composition (irreg.): 11 7/16 x 9 3/4\" (29 x 24.8 cm); page: 13 3/16 x 10 1/16\" (33.5 x 25.5 cm)",
            "Credit": "The Louis E. Stern Collection",
            "Object number": "1002.1964.A4",
            "Copyright": "\u00a9 2023 Estate of Pablo Picasso / Artists Rights Society (ARS), New York",
            "Department": "Drawings and Prints"
        },
        "Profile": "https://www.moma.org/artists/4609"
    },
    {
        "Artist": "Pablo Picasso",
        "Title": "Head from the illustrated book Six Contes Fantastiques",
        "Year": "1944-1953",
        "ObjectID": "29889",
        "Work": "https://www.moma.org/collection/works/29889",
        "Thumbnail": "https://www.moma.org/media/W1siZiIsIjE3MzY1MCJdLFsicCIsImNvbnZlcnQiLCItcXVhbGl0eSA5MCAtcmVzaXplIDUxMng1MTJcdTAwM2UiXV0.jpg?sha=b7d56dc12ecba01f",
        "Details": {
            "Medium": "Engraving",
            "Dimensions": "composition (irreg.): 10 1/16 x 9 5/8\" (25.5 x 24.5 cm); page: 13 3/16 x 10 1/16\" (33.5 x 25.5 cm)",
            "Credit": "The Louis E. Stern Collection",
            "Object number": "1002.1964.A5",
            "Copyright": "\u00a9 2023 Estate of Pablo Picasso / Artists Rights Society (ARS), New York",
            "Department": "Drawings and Prints"
        },
        "Profile": "https://www.moma.org/artists/4609"
    },
    {
        "Artist": "Pablo Picasso",
        "Title": "Profile of a Young Girl Crowned with Flowers from the illustrated book Six Contes Fantastiques",
        "Year": "1944-1953",
        "ObjectID": "29890",
        "Work": "https://www.moma.org/collection/works/29890",
        "Thumbnail": "https://www.moma.org/media/W1siZiIsIjE3MzY1MSJdLFsicCIsImNvbnZlcnQiLCItcXVhbGl0eSA5MCAtcmVzaXplIDUxMng1MTJcdTAwM2UiXV0.jpg?sha=dc64258b700f63c2",
        "Details": {
            "Medium": "Engraving",
            "Dimensions": "composition (irreg.): 12 5/8 x 8 1/4\" (32 x 21 cm); page: 13 3/16 x 10 1/16\" (33.5 x 25.5 cm)",
            "Credit": "The Louis E. Stern Collection",
            "Object number": "1002.1964.A6",
            "Copyright": "\u00a9 2023 Estate of Pablo Picasso / Artists Rights Society (ARS), New York",
            "Department": "Drawings and Prints"
        },
        "Profile": "https://www.moma.org/artists/4609"
    }
]