[
    {
        "Artist": "Tadanori Yokoo",
        "Title": "Yukio Mishima, The Aesthetics of End",
        "Year": "1966",
        "ObjectID": "7955",
        "Work": "https://www.moma.org/collection/works/7955",
        "Thumbnail": "https://www.moma.org/media/W1siZiIsIjI1MTIyNCJdLFsicCIsImNvbnZlcnQiLCItcXVhbGl0eSA5MCAtcmVzaXplIDUxMng1MTJcdTAwM2UiXV0.jpg?sha=c903d0248a73dec3"
    },
    {
        "Artist": "Tadanori Yokoo",
        "Title": "Koshimaki-Osen",
        "Year": "1966",
        "ObjectID": "7957",
        "Work": "https://www.moma.org/collection/works/7957",
        "Thumbnail": "https://www.moma.org/media/W1siZiIsIjUxOTQ4NSJdLFsicCIsImNvbnZlcnQiLCItcXVhbGl0eSA5MCAtcmVzaXplIDUxMng1MTJcdTAwM2UiXV0.jpg?sha=ab43841d7fcef017"
    },
    {
        "Artist": "Tadanori Yokoo",
        "Title": "The City and Design, The Wonders of Life on Earth, Isamu Kurita",
        "Year": "1966",
        "ObjectID": "7959",
        "Work": "https://www.moma.org/collection/works/7959",
        "Thumbnail": "https://www.moma.org/media/W1siZiIsIjUxOTQ4NiJdLFsicCIsImNvbnZlcnQiLCItcXVhbGl0eSA5MCAtcmVzaXplIDUxMng1MTJcdTAwM2UiXV0.jpg?sha=a07b4c29633ab04d"
    },
    {
        "Artist": "Tadanori Yokoo",
        "Title": "Takarazuka, Grand Revue",
        "Year": "1966",
        "ObjectID": "8980",
        "Work": "https://www.moma.org/collection/works/8980",
        "Thumbnail": "https://www.moma.org/media/W1siZiIsIjUxOTY1OSJdLFsicCIsImNvbnZlcnQiLCItcXVhbGl0eSA5MCAtcmVzaXplIDUxMng1MTJcdTAwM2UiXV0.jpg?sha=e319cb5c724f16d0"
    },
    {
        "Artist": "Jack Youngerman",
        "Title": "The Paris Review",
        "Year": "1966",
        "ObjectID": "9009",
        "Work": "https://www.moma.org/collection/works/9009",
        "Thumbnail": null
    },
    {
        "Artist": "Jack Youngerman",
        "Title": "April: Black \u2013 White",
        "Year": "1966",
        "ObjectID": "66443",
        "Work": "https://www.moma.org/collection/works/66443",
        "Thumbnail": null
    },
    {
        "Artist": "Jack Youngerman",
        "Title": "August: Black \u2013 White",
        "Year": "1966",
        "ObjectID": "66463",
        "Work": "https://www.moma.org/collection/works/66463",
        "Thumbnail": null
    },
    {
        "Artist": "Jack Youngerman",
        "Title": "Black \u2013 Red",
        "Year": "1966",
        "ObjectID": "66482",
        "Work": "https://www.moma.org/collection/works/66482",
        "Thumbnail": null
    },
    {
        "Artist": "Jack Youngerman",
        "Title": "Blue \u2013 Yellow \u2013 White",
        "Year": "1966",
        "ObjectID": "66500",
        "Work": "https://www.moma.org/collection/works/66500",
        "Thumbnail": null
    },
    {
        "Artist": "Jack Youngerman",
        "Title": "Elegy \u2013 White",
        "Year": "1966",
        "ObjectID": "66522",
        "Work": "https://www.moma.org/collection/works/66522",
        "Thumbnail": null
    },
    {
        "Artist": "Jack Youngerman",
        "Title": "February \u2013 White",
        "Year": "1966",
        "ObjectID": "66546",
        "Work": "https://www.moma.org/collection/works/66546",
        "Thumbnail": null
    },
    {
        "Artist": "Jack Youngerman",
        "Title": "Horizontal Symmetry: Black \u2013 White",
        "Year": "1966",
        "ObjectID": "66561",
        "Work": "https://www.moma.org/collection/works/66561",
        "Thumbnail": null
    },
    {
        "Artist": "Jack Youngerman",
        "Title": "November: Black \u2013 White",
        "Year": "1966",
        "ObjectID": "66596",
        "Work": "https://www.moma.org/collection/works/66596",
        "Thumbnail": null
    },
    {
        "Artist": "Jack Youngerman",
        "Title": "October: Black \u2013 White",
        "Year": "1966",
        "ObjectID": "66624",
        "Work": "https://www.moma.org/collection/works/66624",
        "Thumbnail": null
    },
    {
        "Artist": "Jack Youngerman",
        "Title": "Red \u2013 White",
        "Year": "1966",
        "ObjectID": "66654",
        "Work": "https://www.moma.org/collection/works/66654",
        "Thumbnail": null
    },
    {
        "Artist": "Jack Youngerman",
        "Title": "Vertical Symmetry: White",
        "Year": "1966",
        "ObjectID": "66685",
        "Work": "https://www.moma.org/collection/works/66685",
        "Thumbnail": null
    },
    {
        "Artist": "Jack Youngerman",
        "Title": "White \u2013 Black",
        "Year": "1966",
        "ObjectID": "66700",
        "Work": "https://www.moma.org/collection/works/66700",
        "Thumbnail": null
    },
    {
        "Artist": "Jack Youngerman",
        "Title": "White \u2013 Blue",
        "Year": "1966",
        "ObjectID": "66715",
        "Work": "https://www.moma.org/collection/works/66715",
        "Thumbnail": null
    },
    {
        "Artist": "Jack Youngerman",
        "Title": "White \u2013 Yellow",
        "Year": "1966",
        "ObjectID": "66751",
        "Work": "https://www.moma.org/collection/works/66751",
        "Thumbnail": null
    },
    {
        "Artist": "Jack Youngerman",
        "Title": "Yellow \u2013 White",
        "Year": "1966",
        "ObjectID": "66783",
        "Work": "https://www.moma.org/collection/works/66783",
        "Thumbnail": null
    },
    {
        "Artist": "Peter Young",
        "Title": "\"#1 - 1966\"",
        "Year": "1966",
        "ObjectID": "78877",
        "Work": "https://www.moma.org/collection/works/78877",
        "Thumbnail": "https://www.moma.org/media/W1siZiIsIjE2MjEyMiJdLFsicCIsImNvbnZlcnQiLCItcXVhbGl0eSA5MCAtcmVzaXplIDUxMng1MTJcdTAwM2UiXV0.jpg?sha=066d18c355eeeefa"
    },
    {
        "Artist": "Melvin Zabarsky",
        "Title": "Rosa's Murderers",
        "Year": "1966",
        "ObjectID": "35126",
        "Work": "https://www.moma.org/collection/works/35126",
        "Thumbnail": null
    },
    {
        "Artist": "Norman Zammitt",
        "Title": "Untitled",
        "Year": "1966",
        "ObjectID": "80794",
        "Work": "https://www.moma.org/collection/works/80794",
        "Thumbnail": "https://www.moma.org/media/W1siZiIsIjUxOTUwNCJdLFsicCIsImNvbnZlcnQiLCItcXVhbGl0eSA5MCAtcmVzaXplIDUxMng1MTJcdTAwM2UiXV0.jpg?sha=eb371e51a768505e"
    },
    {
        "Artist": "Marco Zanuso, Richard Sapper",
        "Title": "Grillo Folding Telephone",
        "Year": "1966",
        "ObjectID": "4620",
        "Work": "https://www.moma.org/collection/works/4620",
        "Thumbnail": null
    },
    {
        "Artist": "Marco Zanuso, Richard Sapper",
        "Title": "Grillo Folding Telephone",
        "Year": "1966",
        "ObjectID": "4621",
        "Work": "https://www.moma.org/collection/works/4621",
        "Thumbnail": "https://www.moma.org/media/W1siZiIsIjIxMjAwMCJdLFsicCIsImNvbnZlcnQiLCItcXVhbGl0eSA5MCAtcmVzaXplIDUxMng1MTJcdTAwM2UiXV0.jpg?sha=fb74be4efbe4a293"
    },
    {
        "Artist": "Zdenek Ziegler",
        "Title": "Marketa Lazarova (Poster for the Czechoslovakian film directed by Frantisek Vlacil)",
        "Year": "1966",
        "ObjectID": "180767",
        "Work": "https://www.moma.org/collection/works/180767",
        "Thumbnail": "https://www.moma.org/media/W1siZiIsIjMwMjgwMSJdLFsicCIsImNvbnZlcnQiLCItcXVhbGl0eSA5MCAtcmVzaXplIDUxMng1MTJcdTAwM2UiXV0.jpg?sha=483ff1945fb6c146"
    },
    {
        "Artist": "Zdenek Ziegler",
        "Title": "Spartakus (Poster for Czechoslovak distribution of the 1960 film directed by Stanley Kubric)",
        "Year": "1966",
        "ObjectID": "180768",
        "Work": "https://www.moma.org/collection/works/180768",
        "Thumbnail": "https://www.moma.org/media/W1siZiIsIjI5OTQ4MSJdLFsicCIsImNvbnZlcnQiLCItcXVhbGl0eSA5MCAtcmVzaXplIDUxMng1MTJcdTAwM2UiXV0.jpg?sha=b6667782025442e6"
    },
    {
        "Artist": "Clinton Adams",
        "Title": "Cleft",
        "Year": "1965",
        "ObjectID": "76934",
        "Work": "https://www.moma.org/collection/works/76934",
        "Thumbnail": null
    },
    {
        "Artist": "Clinton Adams",
        "Title": "Circle I",
        "Year": "1965",
        "ObjectID": "76937",
        "Work": "https://www.moma.org/collection/works/76937",
        "Thumbnail": null
    },
    {
        "Artist": "Clinton Adams",
        "Title": "Nocturne",
        "Year": "1965",
        "ObjectID": "76940",
        "Work": "https://www.moma.org/collection/works/76940",
        "Thumbnail": "https://www.moma.org/media/W1siZiIsIjI3NjI5NiJdLFsicCIsImNvbnZlcnQiLCItcXVhbGl0eSA5MCAtcmVzaXplIDUxMng1MTJcdTAwM2UiXV0.jpg?sha=0c8fbb412e942c89"
    },
    {
        "Artist": "Clinton Adams",
        "Title": "Sorceress",
        "Year": "1965",
        "ObjectID": "77222",
        "Work": "https://www.moma.org/collection/works/77222",
        "Thumbnail": "https://www.moma.org/media/W1siZiIsIjI3NjMwMiJdLFsicCIsImNvbnZlcnQiLCItcXVhbGl0eSA5MCAtcmVzaXplIDUxMng1MTJcdTAwM2UiXV0.jpg?sha=3230ea38da6714e5"
    },
    {
        "Artist": "Clinton Adams",
        "Title": "Circle II",
        "Year": "1965",
        "ObjectID": "77223",
        "Work": "https://www.moma.org/collection/works/77223",
        "Thumbnail": "https://www.moma.org/media/W1siZiIsIjI3NjMwMyJdLFsicCIsImNvbnZlcnQiLCItcXVhbGl0eSA5MCAtcmVzaXplIDUxMng1MTJcdTAwM2UiXV0.jpg?sha=afa42ec052f734d9"
    },
    {
        "Artist": "Clinton Adams",
        "Title": "Enchantress",
        "Year": "1965",
        "ObjectID": "77224",
        "Work": "https://www.moma.org/collection/works/77224",
        "Thumbnail": "https://www.moma.org/media/W1siZiIsIjI3NjMwNCJdLFsicCIsImNvbnZlcnQiLCItcXVhbGl0eSA5MCAtcmVzaXplIDUxMng1MTJcdTAwM2UiXV0.jpg?sha=84b3515725284bb6"
    },
    {
        "Artist": "Robert Adams",
        "Title": "Thurman, Colorado",
        "Year": "1965",
        "ObjectID": "56625",
        "Work": "https://www.moma.org/collection/works/56625",
        "Thumbnail": "https://www.moma.org/media/W1siZiIsIjUyNDQxNyJdLFsicCIsImNvbnZlcnQiLCItcXVhbGl0eSA5MCAtcmVzaXplIDUxMng1MTJcdTAwM2UiXV0.jpg?sha=92d42d1be4f2bada"
    },
    {
        "Artist": "Roy Adzak",
        "Title": "Five Split Bottles: White on White",
        "Year": "1965",
        "ObjectID": "78751",
        "Work": "https://www.moma.org/collection/works/78751",
        "Thumbnail": "https://www.moma.org/media/W1siZiIsIjIzMjAzNCJdLFsicCIsImNvbnZlcnQiLCItcXVhbGl0eSA5MCAtcmVzaXplIDUxMng1MTJcdTAwM2UiXV0.jpg?sha=6061983806b43f49"
    },
    {
        "Artist": "Aktualni umeni, Milan Knizak, Jan Mach, Vit Mach, Sonia Svecova, Jan Trtilek",
        "Title": "Aktualni umeni no. 1",
        "Year": "1965",
        "ObjectID": "179880",
        "Work": "https://www.moma.org/collection/works/179880",
        "Thumbnail": "https://www.moma.org/media/W1siZiIsIjI5NTk1NiJdLFsicCIsImNvbnZlcnQiLCItcXVhbGl0eSA5MCAtcmVzaXplIDUxMng1MTJcdTAwM2UiXV0.jpg?sha=a56ed5fa5d15959b"
    },
    {
        "Artist": "Aktualni umeni, Milan Knizak, Jan Mach, Vit Mach, Sonia Svecova, Jan Trtilek",
        "Title": "Aktualni umeni no. 2",
        "Year": "1965",
        "ObjectID": "179881",
        "Work": "https://www.moma.org/collection/works/179881",
        "Thumbnail": "https://www.moma.org/media/W1siZiIsIjI5NTk1NyJdLFsicCIsImNvbnZlcnQiLCItcXVhbGl0eSA5MCAtcmVzaXplIDUxMng1MTJcdTAwM2UiXV0.jpg?sha=b649165f0d328b6e"
    },
    {
        "Artist": "Aktualni umeni, Milan Knizak, Jan Mach, Vit Mach, Sonia Svecova, Jan Trtilek",
        "Title": "Prototype for Aktualni umeni no. 2",
        "Year": "1965",
        "ObjectID": "179882",
        "Work": "https://www.moma.org/collection/works/179882",
        "Thumbnail": "https://www.moma.org/media/W1siZiIsIjI5NTk1OCJdLFsicCIsImNvbnZlcnQiLCItcXVhbGl0eSA5MCAtcmVzaXplIDUxMng1MTJcdTAwM2UiXV0.jpg?sha=82636f719e3fd0cb"
    },
    {
        "Artist": "Anni Albers",
        "Title": "Casement Material",
        "Year": "c. 1960",
        "ObjectID": "3797",
        "Work": "https://www.moma.org/collection/works/3797",
        "Thumbnail": "https://www.moma.org/media/W1siZiIsIjIwMjIxOCJdLFsicCIsImNvbnZlcnQiLCItcXVhbGl0eSA5MCAtcmVzaXplIDUxMng1MTJcdTAwM2UiXV0.jpg?sha=08ce4b1de7fd7070"
    },
    {
        "Artist": "Pierre Alechinsky",
        "Title": "Rectangles and Knots (Rectangles et noeuds) from the book Paroles Peintes II",
        "Year": "1965",
        "ObjectID": "70891",
        "Work": "https://www.moma.org/collection/works/70891",
        "Thumbnail": "https://www.moma.org/media/W1siZiIsIjIxNDI3MyJdLFsicCIsImNvbnZlcnQiLCItcXVhbGl0eSA5MCAtcmVzaXplIDUxMng1MTJcdTAwM2UiXV0.jpg?sha=af0baa092e33a817"
    },
    {
        "Artist": "Pierre Alechinsky",
        "Title": "Ancestor (Ancetre)",
        "Year": "1965",
        "ObjectID": "70904",
        "Work": "https://www.moma.org/collection/works/70904",
        "Thumbnail": "https://www.moma.org/media/W1siZiIsIjIxNDI3NCJdLFsicCIsImNvbnZlcnQiLCItcXVhbGl0eSA5MCAtcmVzaXplIDUxMng1MTJcdTAwM2UiXV0.jpg?sha=872a21c02370078d"
    },
    {
        "Artist": "Pierre Alechinsky",
        "Title": "Amsterdam",
        "Year": "1965",
        "ObjectID": "70920",
        "Work": "https://www.moma.org/collection/works/70920",
        "Thumbnail": "https://www.moma.org/media/W1siZiIsIjIxNDI3NSJdLFsicCIsImNvbnZlcnQiLCItcXVhbGl0eSA5MCAtcmVzaXplIDUxMng1MTJcdTAwM2UiXV0.jpg?sha=99ea79df4c1ea1da"
    },
    {
        "Artist": "John Altoon",
        "Title": "Untitled",
        "Year": "1965",
        "ObjectID": "76950",
        "Work": "https://www.moma.org/collection/works/76950",
        "Thumbnail": null
    },
    {
        "Artist": "John Altoon",
        "Title": "Untitled",
        "Year": "1965",
        "ObjectID": "76953",
        "Work": "https://www.moma.org/collection/works/76953",
        "Thumbnail": null
    },
    {
        "Artist": "John Altoon",
        "Title": "Untitled",
        "Year": "1965",
        "ObjectID": "76956",
        "Work": "https://www.moma.org/collection/works/76956",
        "Thumbnail": null
    },
    {
        "Artist": "John Altoon",
        "Title": "Untitled",
        "Year": "1965",
        "ObjectID": "76959",
        "Work": "https://www.moma.org/collection/works/76959",
        "Thumbnail": null
    },
    {
        "Artist": "John Altoon",
        "Title": "Untitled",
        "Year": "1965",
        "ObjectID": "76962",
        "Work": "https://www.moma.org/collection/works/76962",
        "Thumbnail": null
    },
    {
        "Artist": "John Altoon",
        "Title": "Untitled",
        "Year": "1965",
        "ObjectID": "76965",
        "Work": "https://www.moma.org/collection/works/76965",
        "Thumbnail": null
    }
]