[
    {
        "Artist": "A. Gisiger",
        "Title": "15 Young Swiss Painters",
        "Year": "1960",
        "ObjectID": "6852",
        "Work": "https://www.moma.org/collection/works/6852",
        "Thumbnail": "https://www.moma.org/media/W1siZiIsIjIxMjE5MiJdLFsicCIsImNvbnZlcnQiLCItcXVhbGl0eSA5MCAtcmVzaXplIDUxMng1MTJcdTAwM2UiXV0.jpg?sha=eb12258e08cdc8cc"
    },
    {
        "Artist": "Fritz Glarner",
        "Title": "Tondo",
        "Year": "(c. 1960)",
        "ObjectID": "38213",
        "Work": "https://www.moma.org/collection/works/38213",
        "Thumbnail": "https://www.moma.org/media/W1siZiIsIjI4NjgyNCJdLFsicCIsImNvbnZlcnQiLCItcXVhbGl0eSA5MCAtcmVzaXplIDUxMng1MTJcdTAwM2UiXV0.jpg?sha=2138f5991273a0ff"
    },
    {
        "Artist": "Jean-Luc Godard",
        "Title": "A bout de souffle (Breathless)",
        "Year": "1960",
        "ObjectID": "306307",
        "Work": "https://www.moma.org/collection/works/306307",
        "Thumbnail": null
    },
    {
        "Artist": "Michael Goldberg",
        "Title": "Odes",
        "Year": "1960",
        "ObjectID": "11695",
        "Work": "https://www.moma.org/collection/works/11695",
        "Thumbnail": null
    },
    {
        "Artist": "Leon Golub",
        "Title": "Torso, III",
        "Year": "December 3, 1960",
        "ObjectID": "78865",
        "Work": "https://www.moma.org/collection/works/78865",
        "Thumbnail": "https://www.moma.org/media/W1siZiIsIjE2NTc1NSJdLFsicCIsImNvbnZlcnQiLCItcXVhbGl0eSA5MCAtcmVzaXplIDUxMng1MTJcdTAwM2UiXV0.jpg?sha=ee806a7a3dda7238"
    },
    {
        "Artist": "Alexander Gonda",
        "Title": "Untitled",
        "Year": "1960",
        "ObjectID": "33101",
        "Work": "https://www.moma.org/collection/works/33101",
        "Thumbnail": null
    },
    {
        "Artist": "Sergio Gonzalez-Tornero",
        "Title": "Chaja",
        "Year": "1960",
        "ObjectID": "73123",
        "Work": "https://www.moma.org/collection/works/73123",
        "Thumbnail": "https://www.moma.org/media/W1siZiIsIjIxNTM0OSJdLFsicCIsImNvbnZlcnQiLCItcXVhbGl0eSA5MCAtcmVzaXplIDUxMng1MTJcdTAwM2UiXV0.jpg?sha=9e1c1be062a44814"
    },
    {
        "Artist": "John D. Graham",
        "Title": "Untitled",
        "Year": "n.d.",
        "ObjectID": "38679",
        "Work": "https://www.moma.org/collection/works/38679",
        "Thumbnail": null
    },
    {
        "Artist": "John D. Graham",
        "Title": "Untitled",
        "Year": "(n.d.)",
        "ObjectID": "38822",
        "Work": "https://www.moma.org/collection/works/38822",
        "Thumbnail": null
    },
    {
        "Artist": "John D. Graham",
        "Title": "Untitled",
        "Year": "n.d.",
        "ObjectID": "38823",
        "Work": "https://www.moma.org/collection/works/38823",
        "Thumbnail": null
    },
    {
        "Artist": "Eugene Fernandez Granell",
        "Title": "The Last Haitian Night of King Christophe",
        "Year": "1960",
        "ObjectID": "78775",
        "Work": "https://www.moma.org/collection/works/78775",
        "Thumbnail": "https://www.moma.org/media/W1siZiIsIjIzNzg0OSJdLFsicCIsImNvbnZlcnQiLCItcXVhbGl0eSA5MCAtcmVzaXplIDUxMng1MTJcdTAwM2UiXV0.jpg?sha=856c48de6754134e"
    },
    {
        "Artist": "Helmut A. P. Grieshaber",
        "Title": "Pan",
        "Year": "1960",
        "ObjectID": "60407",
        "Work": "https://www.moma.org/collection/works/60407",
        "Thumbnail": "https://www.moma.org/media/W1siZiIsIjE2MzQzMiJdLFsicCIsImNvbnZlcnQiLCItcXVhbGl0eSA5MCAtcmVzaXplIDUxMng1MTJcdTAwM2UiXV0.jpg?sha=4217bd41658277d2"
    },
    {
        "Artist": "Peter Grippe, Dylan Thomas",
        "Title": "In-text plate (folio 9) from 21 Etchings and Poems",
        "Year": "1960",
        "ObjectID": "11478",
        "Work": "https://www.moma.org/collection/works/11478",
        "Thumbnail": "https://www.moma.org/media/W1siZiIsIjIwNTY3MiJdLFsicCIsImNvbnZlcnQiLCItcXVhbGl0eSA5MCAtcmVzaXplIDUxMng1MTJcdTAwM2UiXV0.jpg?sha=f922924c48e79559"
    },
    {
        "Artist": "Salvatore Grippi, Richard Wilbur",
        "Title": "In-text plate (folio 10) from 21 Etchings and Poems",
        "Year": "1960",
        "ObjectID": "11479",
        "Work": "https://www.moma.org/collection/works/11479",
        "Thumbnail": "https://www.moma.org/media/W1siZiIsIjIwNTY3MyJdLFsicCIsImNvbnZlcnQiLCItcXVhbGl0eSA5MCAtcmVzaXplIDUxMng1MTJcdTAwM2UiXV0.jpg?sha=45f73ec1c2b16a02"
    },
    {
        "Artist": "Jose Guerrero",
        "Title": "Untitled",
        "Year": "1960",
        "ObjectID": "37640",
        "Work": "https://www.moma.org/collection/works/37640",
        "Thumbnail": "https://www.moma.org/media/W1siZiIsIjExNjYzNSJdLFsicCIsImNvbnZlcnQiLCItcXVhbGl0eSA5MCAtcmVzaXplIDUxMng1MTJcdTAwM2UiXV0.jpg?sha=5a38a8866b97c196"
    },
    {
        "Artist": "Hans Haacke",
        "Title": "Untitled",
        "Year": "1960",
        "ObjectID": "68702",
        "Work": "https://www.moma.org/collection/works/68702",
        "Thumbnail": "https://www.moma.org/media/W1siZiIsIjE2MzQ1NSJdLFsicCIsImNvbnZlcnQiLCItcXVhbGl0eSA5MCAtcmVzaXplIDUxMng1MTJcdTAwM2UiXV0.jpg?sha=dc36320fd87e93f0"
    },
    {
        "Artist": "Ernst Haas",
        "Title": "Untitled",
        "Year": "1960",
        "ObjectID": "49418",
        "Work": "https://www.moma.org/collection/works/49418",
        "Thumbnail": "https://www.moma.org/media/W1siZiIsIjE5OTI2NyJdLFsicCIsImNvbnZlcnQiLCItcXVhbGl0eSA5MCAtcmVzaXplIDUxMng1MTJcdTAwM2UiXV0.jpg?sha=afda1e9a70b054fa"
    },
    {
        "Artist": "Otto Herbert Hajek",
        "Title": "Untitled",
        "Year": "1960",
        "ObjectID": "33139",
        "Work": "https://www.moma.org/collection/works/33139",
        "Thumbnail": null
    },
    {
        "Artist": "Hans Hammarskiold",
        "Title": "Park by Chiswick House, London",
        "Year": "1938-60",
        "ObjectID": "53915",
        "Work": "https://www.moma.org/collection/works/53915",
        "Thumbnail": "https://www.moma.org/media/W1siZiIsIjE5OTMyOSJdLFsicCIsImNvbnZlcnQiLCItcXVhbGl0eSA5MCAtcmVzaXplIDUxMng1MTJcdTAwM2UiXV0.jpg?sha=696cd1318376a15c"
    },
    {
        "Artist": "Hans Hammarskiold",
        "Title": "Untitled",
        "Year": "c. 1955",
        "ObjectID": "53927",
        "Work": "https://www.moma.org/collection/works/53927",
        "Thumbnail": "https://www.moma.org/media/W1siZiIsIjI0ODcwMiJdLFsicCIsImNvbnZlcnQiLCItcXVhbGl0eSA5MCAtcmVzaXplIDUxMng1MTJcdTAwM2UiXV0.jpg?sha=02da6ce36aabe205"
    },
    {
        "Artist": "Grace Hartigan",
        "Title": "Cover from Salute",
        "Year": "1960",
        "ObjectID": "11410",
        "Work": "https://www.moma.org/collection/works/11410",
        "Thumbnail": "https://www.moma.org/media/W1siZiIsIjE4OTY0MiJdLFsicCIsImNvbnZlcnQiLCItcXVhbGl0eSA5MCAtcmVzaXplIDUxMng1MTJcdTAwM2UiXV0.jpg?sha=3786a965199390a8"
    },
    {
        "Artist": "Grace Hartigan",
        "Title": "Salute",
        "Year": "1960",
        "ObjectID": "11411",
        "Work": "https://www.moma.org/collection/works/11411",
        "Thumbnail": "https://www.moma.org/media/W1siZiIsIjE5MjExMiJdLFsicCIsImNvbnZlcnQiLCItcXVhbGl0eSA5MCAtcmVzaXplIDUxMng1MTJcdTAwM2UiXV0.jpg?sha=9622500966c51df8"
    },
    {
        "Artist": "Grace Hartigan",
        "Title": "Title page from Salute",
        "Year": "1960",
        "ObjectID": "11412",
        "Work": "https://www.moma.org/collection/works/11412",
        "Thumbnail": "https://www.moma.org/media/W1siZiIsIjE4OTY0NCJdLFsicCIsImNvbnZlcnQiLCItcXVhbGl0eSA5MCAtcmVzaXplIDUxMng1MTJcdTAwM2UiXV0.jpg?sha=03ee79d418c9230b"
    },
    {
        "Artist": "Grace Hartigan",
        "Title": "Plate (folio 8) from Salute",
        "Year": "1960",
        "ObjectID": "11413",
        "Work": "https://www.moma.org/collection/works/11413",
        "Thumbnail": "https://www.moma.org/media/W1siZiIsIjE4OTY0NSJdLFsicCIsImNvbnZlcnQiLCItcXVhbGl0eSA5MCAtcmVzaXplIDUxMng1MTJcdTAwM2UiXV0.jpg?sha=c1bb72c17fac2476"
    },
    {
        "Artist": "Grace Hartigan",
        "Title": "Plate (folio 12) from Salute",
        "Year": "1960",
        "ObjectID": "11414",
        "Work": "https://www.moma.org/collection/works/11414",
        "Thumbnail": "https://www.moma.org/media/W1siZiIsIjE4OTY0NiJdLFsicCIsImNvbnZlcnQiLCItcXVhbGl0eSA5MCAtcmVzaXplIDUxMng1MTJcdTAwM2UiXV0.jpg?sha=c0037ff1458e3a08"
    },
    {
        "Artist": "Grace Hartigan",
        "Title": "Plate (folio 15) from Salute",
        "Year": "1960",
        "ObjectID": "11415",
        "Work": "https://www.moma.org/collection/works/11415",
        "Thumbnail": "https://www.moma.org/media/W1siZiIsIjE4OTY0NyJdLFsicCIsImNvbnZlcnQiLCItcXVhbGl0eSA5MCAtcmVzaXplIDUxMng1MTJcdTAwM2UiXV0.jpg?sha=110aaa583524d566"
    },
    {
        "Artist": "Grace Hartigan",
        "Title": "Untitled from The Hero Leaves His Ship",
        "Year": "1960",
        "ObjectID": "68891",
        "Work": "https://www.moma.org/collection/works/68891",
        "Thumbnail": "https://www.moma.org/media/W1siZiIsIjIyMDczOSJdLFsicCIsImNvbnZlcnQiLCItcXVhbGl0eSA5MCAtcmVzaXplIDUxMng1MTJcdTAwM2UiXV0.jpg?sha=c519be27c614ff91"
    },
    {
        "Artist": "Grace Hartigan",
        "Title": "The Hero Leaves His Ship",
        "Year": "1960",
        "ObjectID": "68892",
        "Work": "https://www.moma.org/collection/works/68892",
        "Thumbnail": null
    },
    {
        "Artist": "Grace Hartigan",
        "Title": "Untitled from The Hero Leaves His Ship",
        "Year": "1960",
        "ObjectID": "68893",
        "Work": "https://www.moma.org/collection/works/68893",
        "Thumbnail": "https://www.moma.org/media/W1siZiIsIjIyMDc0MCJdLFsicCIsImNvbnZlcnQiLCItcXVhbGl0eSA5MCAtcmVzaXplIDUxMng1MTJcdTAwM2UiXV0.jpg?sha=e3d5a903c6b72ee8"
    },
    {
        "Artist": "Grace Hartigan",
        "Title": "Untitled from The Hero Leaves His Ship",
        "Year": "1960",
        "ObjectID": "68894",
        "Work": "https://www.moma.org/collection/works/68894",
        "Thumbnail": "https://www.moma.org/media/W1siZiIsIjIyMDc0MSJdLFsicCIsImNvbnZlcnQiLCItcXVhbGl0eSA5MCAtcmVzaXplIDUxMng1MTJcdTAwM2UiXV0.jpg?sha=6ada8918e1e6fe0c"
    },
    {
        "Artist": "Grace Hartigan",
        "Title": "Untitled from The Hero Leaves His Ship",
        "Year": "1960",
        "ObjectID": "68895",
        "Work": "https://www.moma.org/collection/works/68895",
        "Thumbnail": "https://www.moma.org/media/W1siZiIsIjIyMDc0MiJdLFsicCIsImNvbnZlcnQiLCItcXVhbGl0eSA5MCAtcmVzaXplIDUxMng1MTJcdTAwM2UiXV0.jpg?sha=be101185318e4740"
    },
    {
        "Artist": "Hans Hartung",
        "Title": "Untitled",
        "Year": "1960",
        "ObjectID": "34907",
        "Work": "https://www.moma.org/collection/works/34907",
        "Thumbnail": "https://www.moma.org/media/W1siZiIsIjUxOTQwMyJdLFsicCIsImNvbnZlcnQiLCItcXVhbGl0eSA5MCAtcmVzaXplIDUxMng1MTJcdTAwM2UiXV0.jpg?sha=3579c5b11e5781dc"
    },
    {
        "Artist": "Stanley William Hayter, Jacques-Henri Levesque",
        "Title": "In-text plate (folio 11) from 21 Etchings and Poems",
        "Year": "c. 1950s, published 1960",
        "ObjectID": "11480",
        "Work": "https://www.moma.org/collection/works/11480",
        "Thumbnail": "https://www.moma.org/media/W1siZiIsIjIwNTY3NCJdLFsicCIsImNvbnZlcnQiLCItcXVhbGl0eSA5MCAtcmVzaXplIDUxMng1MTJcdTAwM2UiXV0.jpg?sha=c38ad97b5cb818e8"
    },
    {
        "Artist": "Dave Heath",
        "Title": "New York",
        "Year": "1960",
        "ObjectID": "46971",
        "Work": "https://www.moma.org/collection/works/46971",
        "Thumbnail": "https://www.moma.org/media/W1siZiIsIjI0NTY5MyJdLFsicCIsImNvbnZlcnQiLCItcXVhbGl0eSA5MCAtcmVzaXplIDUxMng1MTJcdTAwM2UiXV0.jpg?sha=5a063b6e1a7be5a9"
    },
    {
        "Artist": "Dave Heath",
        "Title": "Untitled",
        "Year": "1960",
        "ObjectID": "47019",
        "Work": "https://www.moma.org/collection/works/47019",
        "Thumbnail": "https://www.moma.org/media/W1siZiIsIjI0NTY5NiJdLFsicCIsImNvbnZlcnQiLCItcXVhbGl0eSA5MCAtcmVzaXplIDUxMng1MTJcdTAwM2UiXV0.jpg?sha=ee02fd6aa0fdccaf"
    },
    {
        "Artist": "Dave Heath",
        "Title": "Washington Square, New York",
        "Year": "1960",
        "ObjectID": "160146",
        "Work": "https://www.moma.org/collection/works/160146",
        "Thumbnail": "https://www.moma.org/media/W1siZiIsIjI0NTY5MCJdLFsicCIsImNvbnZlcnQiLCItcXVhbGl0eSA5MCAtcmVzaXplIDUxMng1MTJcdTAwM2UiXV0.jpg?sha=e3f1a7febf374749"
    },
    {
        "Artist": "Al Heenan",
        "Title": "LifeLite 88 Raised Reflective Pavement Markers",
        "Year": "1960",
        "ObjectID": "94578",
        "Work": "https://www.moma.org/collection/works/94578",
        "Thumbnail": null
    },
    {
        "Artist": "Auguste Herbin",
        "Title": "Auguste Herbin, Galerie Denise Rene",
        "Year": "1960",
        "ObjectID": "6831",
        "Work": "https://www.moma.org/collection/works/6831",
        "Thumbnail": null
    },
    {
        "Artist": "Eva Hesse",
        "Title": "Untitled",
        "Year": "1960",
        "ObjectID": "78678",
        "Work": "https://www.moma.org/collection/works/78678",
        "Thumbnail": "https://www.moma.org/media/W1siZiIsIjIwODE0NCJdLFsicCIsImNvbnZlcnQiLCItcXVhbGl0eSA5MCAtcmVzaXplIDUxMng1MTJcdTAwM2UiXV0.jpg?sha=6cf28fcde6bc9468"
    },
    {
        "Artist": "Eva Hesse",
        "Title": "Untitled",
        "Year": "1960",
        "ObjectID": "78681",
        "Work": "https://www.moma.org/collection/works/78681",
        "Thumbnail": "https://www.moma.org/media/W1siZiIsIjE3MTEwMSJdLFsicCIsImNvbnZlcnQiLCItcXVhbGl0eSA5MCAtcmVzaXplIDUxMng1MTJcdTAwM2UiXV0.jpg?sha=daf4b6b4abf1ad8d"
    },
    {
        "Artist": "Eva Hesse",
        "Title": "Untitled",
        "Year": "1960",
        "ObjectID": "193588",
        "Work": "https://www.moma.org/collection/works/193588",
        "Thumbnail": "https://www.moma.org/media/W1siZiIsIjMzMDU4MyJdLFsicCIsImNvbnZlcnQiLCItcXVhbGl0eSA5MCAtcmVzaXplIDUxMng1MTJcdTAwM2UiXV0.jpg?sha=013b037e7bf8dfd1"
    },
    {
        "Artist": "Anton Heyboer",
        "Title": "Yellowing Spirit",
        "Year": "1960",
        "ObjectID": "60458",
        "Work": "https://www.moma.org/collection/works/60458",
        "Thumbnail": "https://www.moma.org/media/W1siZiIsIjE2NjIxNiJdLFsicCIsImNvbnZlcnQiLCItcXVhbGl0eSA5MCAtcmVzaXplIDUxMng1MTJcdTAwM2UiXV0.jpg?sha=eabbc0b66bbe745b"
    },
    {
        "Artist": "Anton Heyboer",
        "Title": "Untitled",
        "Year": "1960",
        "ObjectID": "77389",
        "Work": "https://www.moma.org/collection/works/77389",
        "Thumbnail": "https://www.moma.org/media/W1siZiIsIjIyMTMxNiJdLFsicCIsImNvbnZlcnQiLCItcXVhbGl0eSA5MCAtcmVzaXplIDUxMng1MTJcdTAwM2UiXV0.jpg?sha=9bbb1292fe702dc4"
    },
    {
        "Artist": "Nankoku Hidai",
        "Title": "Work 60 B",
        "Year": "1960",
        "ObjectID": "33010",
        "Work": "https://www.moma.org/collection/works/33010",
        "Thumbnail": null
    },
    {
        "Artist": "Nankoku Hidai",
        "Title": "Work 60 C",
        "Year": "1960",
        "ObjectID": "33024",
        "Work": "https://www.moma.org/collection/works/33024",
        "Thumbnail": "https://www.moma.org/media/W1siZiIsIjQ3ODg4MCJdLFsicCIsImNvbnZlcnQiLCItcXVhbGl0eSA5MCAtcmVzaXplIDUxMng1MTJcdTAwM2UiXV0.jpg?sha=f4feff7d0cba0fe5"
    },
    {
        "Artist": "Nankoku Hidai",
        "Title": "Work 60 D",
        "Year": "1960",
        "ObjectID": "34142",
        "Work": "https://www.moma.org/collection/works/34142",
        "Thumbnail": "https://www.moma.org/media/W1siZiIsIjQ3ODg2NSJdLFsicCIsImNvbnZlcnQiLCItcXVhbGl0eSA5MCAtcmVzaXplIDUxMng1MTJcdTAwM2UiXV0.jpg?sha=8553cb7823896bd3"
    },
    {
        "Artist": "Dick Higgins",
        "Title": "Graphis No. 82",
        "Year": "1960",
        "ObjectID": "127386",
        "Work": "https://www.moma.org/collection/works/127386",
        "Thumbnail": "https://www.moma.org/media/W1siZiIsIjI0NjUzOCJdLFsicCIsImNvbnZlcnQiLCItcXVhbGl0eSA5MCAtcmVzaXplIDUxMng1MTJcdTAwM2UiXV0.jpg?sha=20af636d0e5cd03f"
    },
    {
        "Artist": "Edward Higgins",
        "Title": "Double Portrait -- Torsos",
        "Year": "1960",
        "ObjectID": "80972",
        "Work": "https://www.moma.org/collection/works/80972",
        "Thumbnail": null
    }
]