[
    {
        "Artist": "Ansel Adams",
        "Title": "Sierra Meadow",
        "Year": "1930",
        "ObjectID": "54822",
        "Work": "https://www.moma.org/collection/works/54822",
        "Thumbnail": "https://www.moma.org/media/W1siZiIsIjE5ODI0NyJdLFsicCIsImNvbnZlcnQiLCItcXVhbGl0eSA5MCAtcmVzaXplIDUxMng1MTJcdTAwM2UiXV0.jpg?sha=57faace052a85d58"
    },
    {
        "Artist": "Anni Albers",
        "Title": "Design for Tablecloth",
        "Year": "1930",
        "ObjectID": "3491",
        "Work": "https://www.moma.org/collection/works/3491",
        "Thumbnail": "https://www.moma.org/media/W1siZiIsIjUxNzc2MCJdLFsicCIsImNvbnZlcnQiLCItcXVhbGl0eSA5MCAtcmVzaXplIDUxMng1MTJcdTAwM2UiXV0.jpg?sha=bb0f9a145562ad1c"
    },
    {
        "Artist": "Anni Albers",
        "Title": "Design for Tablecloth",
        "Year": "1930",
        "ObjectID": "3733",
        "Work": "https://www.moma.org/collection/works/3733",
        "Thumbnail": "https://www.moma.org/media/W1siZiIsIjUxNzc1NCJdLFsicCIsImNvbnZlcnQiLCItcXVhbGl0eSA5MCAtcmVzaXplIDUxMng1MTJcdTAwM2UiXV0.jpg?sha=fdd1d510eb3e97a9"
    },
    {
        "Artist": "Anni Albers",
        "Title": "Tablecloth Fabric Sample",
        "Year": "1930",
        "ObjectID": "4099",
        "Work": "https://www.moma.org/collection/works/4099",
        "Thumbnail": "https://www.moma.org/media/W1siZiIsIjUxNzgyMiJdLFsicCIsImNvbnZlcnQiLCItcXVhbGl0eSA5MCAtcmVzaXplIDUxMng1MTJcdTAwM2UiXV0.jpg?sha=6f95b5c79070d284"
    },
    {
        "Artist": "Manuel Alvarez Bravo",
        "Title": "Laughing Mannequins",
        "Year": "1930",
        "ObjectID": "49653",
        "Work": "https://www.moma.org/collection/works/49653",
        "Thumbnail": "https://www.moma.org/media/W1siZiIsIjQ0MzgxMSJdLFsicCIsImNvbnZlcnQiLCItcXVhbGl0eSA5MCAtcmVzaXplIDUxMng1MTJcdTAwM2UiXV0.jpg?sha=fcb4b6b630f7f4e7"
    },
    {
        "Artist": "Tarsila do Amaral",
        "Title": "Study for Composition (Lonely Figure) III (Estudo de Composicao [Figura so] III)",
        "Year": "1930",
        "ObjectID": "199884",
        "Work": "https://www.moma.org/collection/works/199884",
        "Thumbnail": "https://www.moma.org/media/W1siZiIsIjQwMDU4NSJdLFsicCIsImNvbnZlcnQiLCItcXVhbGl0eSA5MCAtcmVzaXplIDUxMng1MTJcdTAwM2UiXV0.jpg?sha=eab7ff80b0befe71"
    },
    {
        "Artist": "Andronova, Raspopina, Sigina, Various Artists",
        "Title": "Tekhnik poligrafist. Gazeta studentov, rabochikh, sluzhashchikh i pedagogov poligraf-tekhnikuma v moskve (The Art of the Printer: Newspaper of the Students, Workers, Employees and Teachers of the Polygraphic-Technical School in Moscow), no. 3",
        "Year": "1930",
        "ObjectID": "32049",
        "Work": "https://www.moma.org/collection/works/32049",
        "Thumbnail": "https://www.moma.org/media/W1siZiIsIjIzMDAxNCJdLFsicCIsImNvbnZlcnQiLCItcXVhbGl0eSA5MCAtcmVzaXplIDUxMng1MTJcdTAwM2UiXV0.jpg?sha=efc63058043c790e"
    },
    {
        "Artist": "Gertrud Arndt",
        "Title": "At the Masters' Houses",
        "Year": "1929-30",
        "ObjectID": "83965",
        "Work": "https://www.moma.org/collection/works/83965",
        "Thumbnail": "https://www.moma.org/media/W1siZiIsIjE1NjMyNSJdLFsicCIsImNvbnZlcnQiLCItcXVhbGl0eSA5MCAtcmVzaXplIDUxMng1MTJcdTAwM2UiXV0.jpg?sha=b7f987ad4b411dce"
    },
    {
        "Artist": "Gertrud Arndt",
        "Title": "Untitled (Masked Self-Portrait, Dessau)",
        "Year": "1930",
        "ObjectID": "407375",
        "Work": "https://www.moma.org/collection/works/407375",
        "Thumbnail": "https://www.moma.org/media/W1siZiIsIjQ5MjAyMCJdLFsicCIsImNvbnZlcnQiLCItcXVhbGl0eSA5MCAtcmVzaXplIDUxMng1MTJcdTAwM2UiXV0.jpg?sha=84cf215b1bbaaf6f"
    },
    {
        "Artist": "Gerd Arntz",
        "Title": "Wohnung und Stadtebau: Dauerausstellung des Gesellschafts- und Wirtschaftsmuseums",
        "Year": "1928-1930",
        "ObjectID": "8690",
        "Work": "https://www.moma.org/collection/works/8690",
        "Thumbnail": "https://www.moma.org/media/W1siZiIsIjUzMDEwMSJdLFsicCIsImNvbnZlcnQiLCItcXVhbGl0eSA5MCAtcmVzaXplIDUxMng1MTJcdTAwM2UiXV0.jpg?sha=7a5df1deb4629ce7"
    },
    {
        "Artist": "Jean (Hans) Arp",
        "Title": "Objects Arranged According to the Law of Chance",
        "Year": "1930",
        "ObjectID": "80912",
        "Work": "https://www.moma.org/collection/works/80912",
        "Thumbnail": "https://www.moma.org/media/W1siZiIsIjIxMDE5NCJdLFsicCIsImNvbnZlcnQiLCItcXVhbGl0eSA5MCAtcmVzaXplIDUxMng1MTJcdTAwM2UiXV0.jpg?sha=b3073e2557643a74"
    },
    {
        "Artist": "Erik Gunnar Asplund",
        "Title": "Stockholm Exhibition, Stockholm, Sweden (Elevation of advertising tower)",
        "Year": "1930",
        "ObjectID": "134",
        "Work": "https://www.moma.org/collection/works/134",
        "Thumbnail": "https://www.moma.org/media/W1siZiIsIjUyNzE3NCJdLFsicCIsImNvbnZlcnQiLCItcXVhbGl0eSA5MCAtcmVzaXplIDUxMng1MTJcdTAwM2UiXV0.jpg?sha=85b87584e0a0addb"
    },
    {
        "Artist": "George Ault",
        "Title": "Lower Manhattan",
        "Year": "1930",
        "ObjectID": "71709",
        "Work": "https://www.moma.org/collection/works/71709",
        "Thumbnail": "https://www.moma.org/media/W1siZiIsIjI1NTUxNyJdLFsicCIsImNvbnZlcnQiLCItcXVhbGl0eSA5MCAtcmVzaXplIDUxMng1MTJcdTAwM2UiXV0.jpg?sha=51e7269d9374157c"
    },
    {
        "Artist": "Peggy Bacon",
        "Title": "Rural Retreat",
        "Year": "1930",
        "ObjectID": "71718",
        "Work": "https://www.moma.org/collection/works/71718",
        "Thumbnail": "https://www.moma.org/media/W1siZiIsIjI2MjM4NyJdLFsicCIsImNvbnZlcnQiLCItcXVhbGl0eSA5MCAtcmVzaXplIDUxMng1MTJcdTAwM2UiXV0.jpg?sha=edfefa61eda97bb0"
    },
    {
        "Artist": "Peggy Bacon",
        "Title": "Heywood Broun",
        "Year": "1930",
        "ObjectID": "71956",
        "Work": "https://www.moma.org/collection/works/71956",
        "Thumbnail": "https://www.moma.org/media/W1siZiIsIjE5NTg4NCJdLFsicCIsImNvbnZlcnQiLCItcXVhbGl0eSA5MCAtcmVzaXplIDUxMng1MTJcdTAwM2UiXV0.jpg?sha=1febffb6b56fcffe"
    },
    {
        "Artist": "Peggy Bacon",
        "Title": "Peanuts",
        "Year": "1930",
        "ObjectID": "71969",
        "Work": "https://www.moma.org/collection/works/71969",
        "Thumbnail": "https://www.moma.org/media/W1siZiIsIjI2MjQxNSJdLFsicCIsImNvbnZlcnQiLCItcXVhbGl0eSA5MCAtcmVzaXplIDUxMng1MTJcdTAwM2UiXV0.jpg?sha=1922344bcf846b71"
    },
    {
        "Artist": "Peggy Bacon",
        "Title": "Slovenliness",
        "Year": "1930",
        "ObjectID": "71986",
        "Work": "https://www.moma.org/collection/works/71986",
        "Thumbnail": "https://www.moma.org/media/W1siZiIsIjI2MjQxNiJdLFsicCIsImNvbnZlcnQiLCItcXVhbGl0eSA5MCAtcmVzaXplIDUxMng1MTJcdTAwM2UiXV0.jpg?sha=e59e693f067c63fc"
    },
    {
        "Artist": "Peggy Bacon",
        "Title": "Happy Holiday",
        "Year": "1930",
        "ObjectID": "72000",
        "Work": "https://www.moma.org/collection/works/72000",
        "Thumbnail": "https://www.moma.org/media/W1siZiIsIjIxNDI4OSJdLFsicCIsImNvbnZlcnQiLCItcXVhbGl0eSA5MCAtcmVzaXplIDUxMng1MTJcdTAwM2UiXV0.jpg?sha=b13d02401cdd269f"
    },
    {
        "Artist": "Ernst Barlach",
        "Title": "King's Grave (Konigsgrab)",
        "Year": "(1930)",
        "ObjectID": "66095",
        "Work": "https://www.moma.org/collection/works/66095",
        "Thumbnail": "https://www.moma.org/media/W1siZiIsIjEzMzcxMyJdLFsicCIsImNvbnZlcnQiLCItcXVhbGl0eSA5MCAtcmVzaXplIDUxMng1MTJcdTAwM2UiXV0.jpg?sha=94c82520e02a8a9e"
    },
    {
        "Artist": "Herbert Bayer",
        "Title": "Section Allemande",
        "Year": "1930",
        "ObjectID": "7117",
        "Work": "https://www.moma.org/collection/works/7117",
        "Thumbnail": "https://www.moma.org/media/W1siZiIsIjUyNjc4MyJdLFsicCIsImNvbnZlcnQiLCItcXVhbGl0eSA5MCAtcmVzaXplIDUxMng1MTJcdTAwM2UiXV0.jpg?sha=0969cc712c83fcb9"
    },
    {
        "Artist": "Herbert Bayer",
        "Title": "Bauhausbucher 9, \"Punkt und Linie zu Flache\" by Vasily Kandinsky. Bauhaus Books, 2nd edition",
        "Year": "1928",
        "ObjectID": "7355",
        "Work": "https://www.moma.org/collection/works/7355",
        "Thumbnail": "https://www.moma.org/media/W1siZiIsIjUyODU1NyJdLFsicCIsImNvbnZlcnQiLCItcXVhbGl0eSA5MCAtcmVzaXplIDUxMng1MTJcdTAwM2UiXV0.jpg?sha=2dfcceabd7294e83"
    },
    {
        "Artist": "Herbert Bayer",
        "Title": "Mit Zuversicht in's neue Jahr Dorland wunscht viel Gluck, 1930-1931",
        "Year": "1930",
        "ObjectID": "7458",
        "Work": "https://www.moma.org/collection/works/7458",
        "Thumbnail": "https://www.moma.org/media/W1siZiIsIjUyODU3OSJdLFsicCIsImNvbnZlcnQiLCItcXVhbGl0eSA5MCAtcmVzaXplIDUxMng1MTJcdTAwM2UiXV0.jpg?sha=cc79c32be919e6e3"
    },
    {
        "Artist": "Herbert Bayer",
        "Title": "Die neue Linie, Marz 1930",
        "Year": "1930",
        "ObjectID": "7462",
        "Work": "https://www.moma.org/collection/works/7462",
        "Thumbnail": "https://www.moma.org/media/W1siZiIsIjUyODU4MCJdLFsicCIsImNvbnZlcnQiLCItcXVhbGl0eSA5MCAtcmVzaXplIDUxMng1MTJcdTAwM2UiXV0.jpg?sha=e35808d83d97b78c"
    },
    {
        "Artist": "Herbert Bayer",
        "Title": "Die neue Linie, Mai 1930",
        "Year": "1930",
        "ObjectID": "7470",
        "Work": "https://www.moma.org/collection/works/7470",
        "Thumbnail": "https://www.moma.org/media/W1siZiIsIjUyODU4MSJdLFsicCIsImNvbnZlcnQiLCItcXVhbGl0eSA5MCAtcmVzaXplIDUxMng1MTJcdTAwM2UiXV0.jpg?sha=30db25c86139ea38"
    },
    {
        "Artist": "Herbert Bayer",
        "Title": "DWB 19. Jahresversammlung",
        "Year": "1930",
        "ObjectID": "7475",
        "Work": "https://www.moma.org/collection/works/7475",
        "Thumbnail": "https://www.moma.org/media/W1siZiIsIjUyODU4MiJdLFsicCIsImNvbnZlcnQiLCItcXVhbGl0eSA5MCAtcmVzaXplIDUxMng1MTJcdTAwM2UiXV0.jpg?sha=cfe024a2038c4a1f"
    },
    {
        "Artist": "Herbert Bayer",
        "Title": "Adler Werke, Berlin letterhead",
        "Year": "1931",
        "ObjectID": "7485",
        "Work": "https://www.moma.org/collection/works/7485",
        "Thumbnail": "https://www.moma.org/media/W1siZiIsIjUyODU4NCJdLFsicCIsImNvbnZlcnQiLCItcXVhbGl0eSA5MCAtcmVzaXplIDUxMng1MTJcdTAwM2UiXV0.jpg?sha=5bc88bba57afc879"
    },
    {
        "Artist": "Herbert Bayer",
        "Title": "Anbaumobel, Entwurf: Walter Gropius, Prof. Dr. e.H (Brochure promoting modular furniture designed by Walter Gropius for the Berlin firm Feder)",
        "Year": "1930",
        "ObjectID": "7547",
        "Work": "https://www.moma.org/collection/works/7547",
        "Thumbnail": "https://www.moma.org/media/W1siZiIsIjUyODYwMCJdLFsicCIsImNvbnZlcnQiLCItcXVhbGl0eSA5MCAtcmVzaXplIDUxMng1MTJcdTAwM2UiXV0.jpg?sha=450971b8120673b0"
    },
    {
        "Artist": "Herbert Bayer",
        "Title": "Sundeck",
        "Year": "1930",
        "ObjectID": "48467",
        "Work": "https://www.moma.org/collection/works/48467",
        "Thumbnail": "https://www.moma.org/media/W1siZiIsIjE1NjMzNCJdLFsicCIsImNvbnZlcnQiLCItcXVhbGl0eSA5MCAtcmVzaXplIDUxMng1MTJcdTAwM2UiXV0.jpg?sha=74e8f7866f78eede"
    },
    {
        "Artist": "Herbert Bayer",
        "Title": "Adler Typewriters letterhead",
        "Year": "1930",
        "ObjectID": "198491",
        "Work": "https://www.moma.org/collection/works/198491",
        "Thumbnail": "https://www.moma.org/media/W1siZiIsIjM0MzA3MyJdLFsicCIsImNvbnZlcnQiLCItcXVhbGl0eSA5MCAtcmVzaXplIDUxMng1MTJcdTAwM2UiXV0.jpg?sha=de0293ba2f5c80dc"
    },
    {
        "Artist": "Eugene Berman",
        "Title": "The Good Samaritan",
        "Year": "1930",
        "ObjectID": "79294",
        "Work": "https://www.moma.org/collection/works/79294",
        "Thumbnail": "https://www.moma.org/media/W1siZiIsIjIwODYyOCJdLFsicCIsImNvbnZlcnQiLCItcXVhbGl0eSA5MCAtcmVzaXplIDUxMng1MTJcdTAwM2UiXV0.jpg?sha=664f71808431fce4"
    },
    {
        "Artist": "Eugene Berman",
        "Title": "The Cart",
        "Year": "1930",
        "ObjectID": "80583",
        "Work": "https://www.moma.org/collection/works/80583",
        "Thumbnail": "https://www.moma.org/media/W1siZiIsIjIwOTU3MSJdLFsicCIsImNvbnZlcnQiLCItcXVhbGl0eSA5MCAtcmVzaXplIDUxMng1MTJcdTAwM2UiXV0.jpg?sha=e5a96a4fe05eb049"
    },
    {
        "Artist": "Bettmann/United Press International",
        "Title": "\"Another Little Democrat in the Family\"",
        "Year": "May 1930",
        "ObjectID": "58546",
        "Work": "https://www.moma.org/collection/works/58546",
        "Thumbnail": "https://www.moma.org/media/W1siZiIsIjIxODM0NSJdLFsicCIsImNvbnZlcnQiLCItcXVhbGl0eSA5MCAtcmVzaXplIDUxMng1MTJcdTAwM2UiXV0.jpg?sha=9256713f9d9105b0"
    },
    {
        "Artist": "Aenne Biermann",
        "Title": "Summer Swimming",
        "Year": "1925-30",
        "ObjectID": "83711",
        "Work": "https://www.moma.org/collection/works/83711",
        "Thumbnail": "https://www.moma.org/media/W1siZiIsIjIwMDY2OCJdLFsicCIsImNvbnZlcnQiLCItcXVhbGl0eSA5MCAtcmVzaXplIDUxMng1MTJcdTAwM2UiXV0.jpg?sha=04c438cd1b37154c"
    },
    {
        "Artist": "Blanc et Demilly",
        "Title": "Lustucru Pasta",
        "Year": "1930",
        "ObjectID": "83717",
        "Work": "https://www.moma.org/collection/works/83717",
        "Thumbnail": "https://www.moma.org/media/W1siZiIsIjE4NjQ2MSJdLFsicCIsImNvbnZlcnQiLCItcXVhbGl0eSA5MCAtcmVzaXplIDUxMng1MTJcdTAwM2UiXV0.jpg?sha=54aa4f368991f98e"
    },
    {
        "Artist": "Peter Blume",
        "Title": "Parade",
        "Year": "1930",
        "ObjectID": "78560",
        "Work": "https://www.moma.org/collection/works/78560",
        "Thumbnail": "https://www.moma.org/media/W1siZiIsIjIwODA0NSJdLFsicCIsImNvbnZlcnQiLCItcXVhbGl0eSA5MCAtcmVzaXplIDUxMng1MTJcdTAwM2UiXV0.jpg?sha=882ee4a238ceb0d2"
    },
    {
        "Artist": "Margaret Bourke-White",
        "Title": "A Generator Shell, Dnieperstroi",
        "Year": "1930",
        "ObjectID": "46964",
        "Work": "https://www.moma.org/collection/works/46964",
        "Thumbnail": "https://www.moma.org/media/W1siZiIsIjUyMDEzOSJdLFsicCIsImNvbnZlcnQiLCItcXVhbGl0eSA5MCAtcmVzaXplIDUxMng1MTJcdTAwM2UiXV0.jpg?sha=f8b9f2eb4b9e4a9c"
    },
    {
        "Artist": "Margaret Bourke-White",
        "Title": "Iron Puddler, Red October Rolling Mills, Stalingrad",
        "Year": "1930",
        "ObjectID": "46976",
        "Work": "https://www.moma.org/collection/works/46976",
        "Thumbnail": "https://www.moma.org/media/W1siZiIsIjE5NzczOCJdLFsicCIsImNvbnZlcnQiLCItcXVhbGl0eSA5MCAtcmVzaXplIDUxMng1MTJcdTAwM2UiXV0.jpg?sha=52a58ae737fed04e"
    },
    {
        "Artist": "Margaret Bourke-White",
        "Title": "Brekekekex-koax-koax",
        "Year": "1930",
        "ObjectID": "83684",
        "Work": "https://www.moma.org/collection/works/83684",
        "Thumbnail": "https://www.moma.org/media/W1siZiIsIjIwMDY3MiJdLFsicCIsImNvbnZlcnQiLCItcXVhbGl0eSA5MCAtcmVzaXplIDUxMng1MTJcdTAwM2UiXV0.jpg?sha=eaa2c29ef20e7b60"
    },
    {
        "Artist": "Constantin Brancusi",
        "Title": "Fish",
        "Year": "Paris 1930",
        "ObjectID": "81795",
        "Work": "https://www.moma.org/collection/works/81795",
        "Thumbnail": "https://www.moma.org/media/W1siZiIsIjE1OTE0MyJdLFsicCIsImNvbnZlcnQiLCItcXVhbGl0eSA5MCAtcmVzaXplIDUxMng1MTJcdTAwM2UiXV0.jpg?sha=de67ae7a87b3445d"
    },
    {
        "Artist": "Bill Brandt",
        "Title": "Hungary",
        "Year": "c. 1930",
        "ObjectID": "104297",
        "Work": "https://www.moma.org/collection/works/104297",
        "Thumbnail": "https://www.moma.org/media/W1siZiIsIjE4NDM4MCJdLFsicCIsImNvbnZlcnQiLCItcXVhbGl0eSA5MCAtcmVzaXplIDUxMng1MTJcdTAwM2UiXV0.jpg?sha=c41826886a22368a"
    },
    {
        "Artist": "Patrick Henry Bruce",
        "Title": "Painting",
        "Year": "c. 1929-30",
        "ObjectID": "79208",
        "Work": "https://www.moma.org/collection/works/79208",
        "Thumbnail": "https://www.moma.org/media/W1siZiIsIjMyNDc2MiJdLFsicCIsImNvbnZlcnQiLCItcXVhbGl0eSA5MCAtcmVzaXplIDUxMng1MTJcdTAwM2UiXV0.jpg?sha=4fdbe4026b36c6e8"
    },
    {
        "Artist": "Francis Bruguiere",
        "Title": "Light Abstraction",
        "Year": "c. 1925",
        "ObjectID": "53928",
        "Work": "https://www.moma.org/collection/works/53928",
        "Thumbnail": "https://www.moma.org/media/W1siZiIsIjIwNzYzMSJdLFsicCIsImNvbnZlcnQiLCItcXVhbGl0eSA5MCAtcmVzaXplIDUxMng1MTJcdTAwM2UiXV0.jpg?sha=0b2d58d2cf6e88a9"
    },
    {
        "Artist": "Francis Bruguiere",
        "Title": "Light Abstraction",
        "Year": "c. 1925",
        "ObjectID": "53940",
        "Work": "https://www.moma.org/collection/works/53940",
        "Thumbnail": "https://www.moma.org/media/W1siZiIsIjIwNzYzMiJdLFsicCIsImNvbnZlcnQiLCItcXVhbGl0eSA5MCAtcmVzaXplIDUxMng1MTJcdTAwM2UiXV0.jpg?sha=bbb2873d145bd760"
    },
    {
        "Artist": "Eugene Buechel",
        "Title": "Sam Spotted Warbonnet After Accident",
        "Year": "February 26, 1930",
        "ObjectID": "45442",
        "Work": "https://www.moma.org/collection/works/45442",
        "Thumbnail": "https://www.moma.org/media/W1siZiIsIjE4NjU3MyJdLFsicCIsImNvbnZlcnQiLCItcXVhbGl0eSA5MCAtcmVzaXplIDUxMng1MTJcdTAwM2UiXV0.jpg?sha=6c343e7aa5dcdc1c"
    },
    {
        "Artist": "Eugene Buechel",
        "Title": "Easter Dinner in Front of Cutmeat Church",
        "Year": "April 20, 1930",
        "ObjectID": "45443",
        "Work": "https://www.moma.org/collection/works/45443",
        "Thumbnail": "https://www.moma.org/media/W1siZiIsIjE4NjU3NCJdLFsicCIsImNvbnZlcnQiLCItcXVhbGl0eSA5MCAtcmVzaXplIDUxMng1MTJcdTAwM2UiXV0.jpg?sha=005ba794784ae701"
    },
    {
        "Artist": "Eugene Buechel",
        "Title": "Viola Manning, Alice Boyle, Amelian Schaffer, and Crowd at Spring Creek",
        "Year": "August 18, 1930",
        "ObjectID": "45452",
        "Work": "https://www.moma.org/collection/works/45452",
        "Thumbnail": "https://www.moma.org/media/W1siZiIsIjE3MDQyNSJdLFsicCIsImNvbnZlcnQiLCItcXVhbGl0eSA5MCAtcmVzaXplIDUxMng1MTJcdTAwM2UiXV0.jpg?sha=4729b72a86752c5b"
    },
    {
        "Artist": "Luis Bunuel",
        "Title": "L'Age d'or",
        "Year": "1930",
        "ObjectID": "306159",
        "Work": "https://www.moma.org/collection/works/306159",
        "Thumbnail": "https://www.moma.org/media/W1siZiIsIjExMjk3NiJdLFsicCIsImNvbnZlcnQiLCItcXVhbGl0eSA5MCAtcmVzaXplIDUxMng1MTJcdTAwM2UiXV0.jpg?sha=dd28eaa019f6717b"
    },
    {
        "Artist": "Max Burchartz",
        "Title": "Europas grosste industriekonzerne Besitzen Europas hochste Schornsteine",
        "Year": "Before 1930, probably 1928",
        "ObjectID": "7735",
        "Work": "https://www.moma.org/collection/works/7735",
        "Thumbnail": "https://www.moma.org/media/W1siZiIsIjUzMDc0MSJdLFsicCIsImNvbnZlcnQiLCItcXVhbGl0eSA5MCAtcmVzaXplIDUxMng1MTJcdTAwM2UiXV0.jpg?sha=7c358b0509427d89"
    }
]