[
    {
        "Artist": "Josef Albers",
        "Title": "Mitered Square f from Mitered Squares",
        "Year": "1976",
        "ObjectID": "139840",
        "Work": "https://www.moma.org/collection/works/139840",
        "Thumbnail": "https://www.moma.org/media/W1siZiIsIjE5NTg1OCJdLFsicCIsImNvbnZlcnQiLCItcXVhbGl0eSA5MCAtcmVzaXplIDUxMng1MTJcdTAwM2UiXV0.jpg?sha=9cbc791dd954aacd"
    },
    {
        "Artist": "Josef Albers",
        "Title": "Mitered Square a from Mitered Square",
        "Year": "1976",
        "ObjectID": "139841",
        "Work": "https://www.moma.org/collection/works/139841",
        "Thumbnail": "https://www.moma.org/media/W1siZiIsIjE5NTg1OSJdLFsicCIsImNvbnZlcnQiLCItcXVhbGl0eSA5MCAtcmVzaXplIDUxMng1MTJcdTAwM2UiXV0.jpg?sha=49f638e499417731"
    },
    {
        "Artist": "Josef Albers",
        "Title": "Mitered Square d from Mitered Squares",
        "Year": "1976",
        "ObjectID": "139842",
        "Work": "https://www.moma.org/collection/works/139842",
        "Thumbnail": "https://www.moma.org/media/W1siZiIsIjE5NTg2MCJdLFsicCIsImNvbnZlcnQiLCItcXVhbGl0eSA5MCAtcmVzaXplIDUxMng1MTJcdTAwM2UiXV0.jpg?sha=b26d7787203dc7ed"
    },
    {
        "Artist": "Josef Albers",
        "Title": "Mitered Square e from Mitered Squares",
        "Year": "1976",
        "ObjectID": "139843",
        "Work": "https://www.moma.org/collection/works/139843",
        "Thumbnail": "https://www.moma.org/media/W1siZiIsIjE5NzM0MSJdLFsicCIsImNvbnZlcnQiLCItcXVhbGl0eSA5MCAtcmVzaXplIDUxMng1MTJcdTAwM2UiXV0.jpg?sha=f05baad611d4cc8a"
    },
    {
        "Artist": "Josef Albers",
        "Title": "Mitered Square g from Mitered Squares",
        "Year": "1976",
        "ObjectID": "139844",
        "Work": "https://www.moma.org/collection/works/139844",
        "Thumbnail": "https://www.moma.org/media/W1siZiIsIjE5NzM0MiJdLFsicCIsImNvbnZlcnQiLCItcXVhbGl0eSA5MCAtcmVzaXplIDUxMng1MTJcdTAwM2UiXV0.jpg?sha=188a7126dc959e99"
    },
    {
        "Artist": "Josef Albers",
        "Title": "Mitered Square h from Mitered Squares",
        "Year": "1976",
        "ObjectID": "139845",
        "Work": "https://www.moma.org/collection/works/139845",
        "Thumbnail": "https://www.moma.org/media/W1siZiIsIjE5NzM0MyJdLFsicCIsImNvbnZlcnQiLCItcXVhbGl0eSA5MCAtcmVzaXplIDUxMng1MTJcdTAwM2UiXV0.jpg?sha=b6572b3e1594e625"
    },
    {
        "Artist": "Josef Albers",
        "Title": "Mitered Square i from Mitered Squares",
        "Year": "1976",
        "ObjectID": "139846",
        "Work": "https://www.moma.org/collection/works/139846",
        "Thumbnail": "https://www.moma.org/media/W1siZiIsIjE5NzM0NCJdLFsicCIsImNvbnZlcnQiLCItcXVhbGl0eSA5MCAtcmVzaXplIDUxMng1MTJcdTAwM2UiXV0.jpg?sha=d812f6aa8553c3de"
    },
    {
        "Artist": "Josef Albers",
        "Title": "Mitered Square j from Mitered Squares",
        "Year": "1976",
        "ObjectID": "139847",
        "Work": "https://www.moma.org/collection/works/139847",
        "Thumbnail": "https://www.moma.org/media/W1siZiIsIjE5NzMzOCJdLFsicCIsImNvbnZlcnQiLCItcXVhbGl0eSA5MCAtcmVzaXplIDUxMng1MTJcdTAwM2UiXV0.jpg?sha=4bf3f086c4d6a0b2"
    },
    {
        "Artist": "Josef Albers",
        "Title": "Mitered Square k from Mitered Square",
        "Year": "1976",
        "ObjectID": "139848",
        "Work": "https://www.moma.org/collection/works/139848",
        "Thumbnail": "https://www.moma.org/media/W1siZiIsIjE5NzMzOSJdLFsicCIsImNvbnZlcnQiLCItcXVhbGl0eSA5MCAtcmVzaXplIDUxMng1MTJcdTAwM2UiXV0.jpg?sha=710965727ba668bb"
    },
    {
        "Artist": "Josef Albers",
        "Title": "Mitered Square l from Mitered Squares",
        "Year": "1976",
        "ObjectID": "139849",
        "Work": "https://www.moma.org/collection/works/139849",
        "Thumbnail": "https://www.moma.org/media/W1siZiIsIjE5NzM0MCJdLFsicCIsImNvbnZlcnQiLCItcXVhbGl0eSA5MCAtcmVzaXplIDUxMng1MTJcdTAwM2UiXV0.jpg?sha=ea5e296f841c3455"
    },
    {
        "Artist": "Allan Alcorn, Unidentified Designer",
        "Title": "Home Pong video game console",
        "Year": "1976",
        "ObjectID": "197768",
        "Work": "https://www.moma.org/collection/works/197768",
        "Thumbnail": "https://www.moma.org/media/W1siZiIsIjUxMjYxOSJdLFsicCIsImNvbnZlcnQiLCItcXVhbGl0eSA5MCAtcmVzaXplIDUxMng1MTJcdTAwM2UiXV0.jpg?sha=bb3ff1f60857ca42"
    },
    {
        "Artist": "Pierre Alechinsky",
        "Title": "Central Park",
        "Year": "1976",
        "ObjectID": "20025",
        "Work": "https://www.moma.org/collection/works/20025",
        "Thumbnail": "https://www.moma.org/media/W1siZiIsIjMxNjEyNyJdLFsicCIsImNvbnZlcnQiLCItcXVhbGl0eSA5MCAtcmVzaXplIDUxMng1MTJcdTAwM2UiXV0.jpg?sha=942952e0bfa93b70"
    },
    {
        "Artist": "Pierre Alechinsky",
        "Title": "Par experience",
        "Year": "1976",
        "ObjectID": "20034",
        "Work": "https://www.moma.org/collection/works/20034",
        "Thumbnail": "https://www.moma.org/media/W1siZiIsIjE4MjI4MCJdLFsicCIsImNvbnZlcnQiLCItcXVhbGl0eSA5MCAtcmVzaXplIDUxMng1MTJcdTAwM2UiXV0.jpg?sha=00df8e13a3f87583"
    },
    {
        "Artist": "Pierre Alechinsky",
        "Title": "Full Page (Pleine page)",
        "Year": "1976",
        "ObjectID": "71704",
        "Work": "https://www.moma.org/collection/works/71704",
        "Thumbnail": "https://www.moma.org/media/W1siZiIsIjIxMzczNiJdLFsicCIsImNvbnZlcnQiLCItcXVhbGl0eSA5MCAtcmVzaXplIDUxMng1MTJcdTAwM2UiXV0.jpg?sha=a20a516dc0ef7fa0"
    },
    {
        "Artist": "Pierre Alechinsky",
        "Title": "Belgian Woman (Brabanconne)",
        "Year": "1976",
        "ObjectID": "71713",
        "Work": "https://www.moma.org/collection/works/71713",
        "Thumbnail": "https://www.moma.org/media/W1siZiIsIjc5NjU0Il0sWyJwIiwiY29udmVydCIsIi1xdWFsaXR5IDkwIC1yZXNpemUgNTEyeDUxMlx1MDAzZSJdXQ.jpg?sha=67e9e6b22f379750"
    },
    {
        "Artist": "Pierre Alechinsky",
        "Title": "Direct Line(Ligne directe)",
        "Year": "1976",
        "ObjectID": "71723",
        "Work": "https://www.moma.org/collection/works/71723",
        "Thumbnail": "https://www.moma.org/media/W1siZiIsIjIxMzczNyJdLFsicCIsImNvbnZlcnQiLCItcXVhbGl0eSA5MCAtcmVzaXplIDUxMng1MTJcdTAwM2UiXV0.jpg?sha=c8e81910ad54f46e"
    },
    {
        "Artist": "Pierre Alechinsky",
        "Title": "Blue Falls (Chute bleue)",
        "Year": "1976",
        "ObjectID": "71744",
        "Work": "https://www.moma.org/collection/works/71744",
        "Thumbnail": "https://www.moma.org/media/W1siZiIsIjc4OTg4Il0sWyJwIiwiY29udmVydCIsIi1xdWFsaXR5IDkwIC1yZXNpemUgNTEyeDUxMlx1MDAzZSJdXQ.jpg?sha=5e9846de517db3ea"
    },
    {
        "Artist": "Pierre Alechinsky",
        "Title": "Breakwater (Estacade)",
        "Year": "1976",
        "ObjectID": "71755",
        "Work": "https://www.moma.org/collection/works/71755",
        "Thumbnail": "https://www.moma.org/media/W1siZiIsIjIxMzc0MCJdLFsicCIsImNvbnZlcnQiLCItcXVhbGl0eSA5MCAtcmVzaXplIDUxMng1MTJcdTAwM2UiXV0.jpg?sha=3680d48b840c65ac"
    },
    {
        "Artist": "Pierre Alechinsky",
        "Title": "L'Eau Douce",
        "Year": "1976",
        "ObjectID": "71767",
        "Work": "https://www.moma.org/collection/works/71767",
        "Thumbnail": "https://www.moma.org/media/W1siZiIsIjc5NjU1Il0sWyJwIiwiY29udmVydCIsIi1xdWFsaXR5IDkwIC1yZXNpemUgNTEyeDUxMlx1MDAzZSJdXQ.jpg?sha=522afb77f580254e"
    },
    {
        "Artist": "Pierre Alechinsky",
        "Title": "Eau Forte",
        "Year": "1976",
        "ObjectID": "71783",
        "Work": "https://www.moma.org/collection/works/71783",
        "Thumbnail": "https://www.moma.org/media/W1siZiIsIjc4OTkxIl0sWyJwIiwiY29udmVydCIsIi1xdWFsaXR5IDkwIC1yZXNpemUgNTEyeDUxMlx1MDAzZSJdXQ.jpg?sha=36c7a97245c3680e"
    },
    {
        "Artist": "Pierre Alechinsky",
        "Title": "Armoured Hat (Chapeau fort)",
        "Year": "1976",
        "ObjectID": "71794",
        "Work": "https://www.moma.org/collection/works/71794",
        "Thumbnail": "https://www.moma.org/media/W1siZiIsIjIxMzc0MiJdLFsicCIsImNvbnZlcnQiLCItcXVhbGl0eSA5MCAtcmVzaXplIDUxMng1MTJcdTAwM2UiXV0.jpg?sha=403b5d3147d9471a"
    },
    {
        "Artist": "Pierre Alechinsky",
        "Title": "Monkey Business II",
        "Year": "1976",
        "ObjectID": "71810",
        "Work": "https://www.moma.org/collection/works/71810",
        "Thumbnail": "https://www.moma.org/media/W1siZiIsIjIxNDI4NiJdLFsicCIsImNvbnZlcnQiLCItcXVhbGl0eSA5MCAtcmVzaXplIDUxMng1MTJcdTAwM2UiXV0.jpg?sha=e465c7b6367097cf"
    },
    {
        "Artist": "Pierre Alechinsky",
        "Title": "Plate I from the series Boreality (Borealite)",
        "Year": "1976",
        "ObjectID": "71821",
        "Work": "https://www.moma.org/collection/works/71821",
        "Thumbnail": "https://www.moma.org/media/W1siZiIsIjI1MTkxOCJdLFsicCIsImNvbnZlcnQiLCItcXVhbGl0eSA5MCAtcmVzaXplIDUxMng1MTJcdTAwM2UiXV0.jpg?sha=a3c4039a8cf8a4fd"
    },
    {
        "Artist": "Pierre Alechinsky",
        "Title": "Boreality (Borealite)",
        "Year": "1976",
        "ObjectID": "71822",
        "Work": "https://www.moma.org/collection/works/71822",
        "Thumbnail": null
    },
    {
        "Artist": "Harry Allen",
        "Title": "Stark County, Toulon, Illinois",
        "Year": "1975-76",
        "ObjectID": "51007",
        "Work": "https://www.moma.org/collection/works/51007",
        "Thumbnail": "https://www.moma.org/media/W1siZiIsIjI0NTAxNCJdLFsicCIsImNvbnZlcnQiLCItcXVhbGl0eSA5MCAtcmVzaXplIDUxMng1MTJcdTAwM2UiXV0.jpg?sha=7c0a6100c6ae7e41"
    },
    {
        "Artist": "Terry Allen",
        "Title": "Juarez",
        "Year": "1976",
        "ObjectID": "18856",
        "Work": "https://www.moma.org/collection/works/18856",
        "Thumbnail": "https://www.moma.org/media/W1siZiIsIjI2MjM4MCJdLFsicCIsImNvbnZlcnQiLCItcXVhbGl0eSA5MCAtcmVzaXplIDUxMng1MTJcdTAwM2UiXV0.jpg?sha=ce3e4506d1ee2456"
    },
    {
        "Artist": "Emilio Ambasz, Giancarlo Piretti",
        "Title": "Vertebra Operational Chair",
        "Year": "1975",
        "ObjectID": "3354",
        "Work": "https://www.moma.org/collection/works/3354",
        "Thumbnail": "https://www.moma.org/media/W1siZiIsIjIyOTM0NCJdLFsicCIsImNvbnZlcnQiLCItcXVhbGl0eSA5MCAtcmVzaXplIDUxMng1MTJcdTAwM2UiXV0.jpg?sha=14020de593a0c094"
    },
    {
        "Artist": "Emilio Ambasz, Giancarlo Piretti",
        "Title": "Vertebra Executive's Chair",
        "Year": "1975",
        "ObjectID": "3360",
        "Work": "https://www.moma.org/collection/works/3360",
        "Thumbnail": "https://www.moma.org/media/W1siZiIsIjUyMTQzNSJdLFsicCIsImNvbnZlcnQiLCItcXVhbGl0eSA5MCAtcmVzaXplIDUxMng1MTJcdTAwM2UiXV0.jpg?sha=fe89c40180ded896"
    },
    {
        "Artist": "Carl Andre",
        "Title": "Untitled from the Rubber Stamp Portfolio",
        "Year": "1976, published 1977",
        "ObjectID": "63832",
        "Work": "https://www.moma.org/collection/works/63832",
        "Thumbnail": "https://www.moma.org/media/W1siZiIsIjI1NzQ1MyJdLFsicCIsImNvbnZlcnQiLCItcXVhbGl0eSA5MCAtcmVzaXplIDUxMng1MTJcdTAwM2UiXV0.jpg?sha=a37997be03314ef6"
    },
    {
        "Artist": "Carl Andre",
        "Title": "44 Nickel Run",
        "Year": "1976",
        "ObjectID": "126404",
        "Work": "https://www.moma.org/collection/works/126404",
        "Thumbnail": null
    },
    {
        "Artist": "Paul Anka, Andy Warhol",
        "Title": "The Painter",
        "Year": "1976",
        "ObjectID": "184615",
        "Work": "https://www.moma.org/collection/works/184615",
        "Thumbnail": "https://www.moma.org/media/W1siZiIsIjM4MDU2OCJdLFsicCIsImNvbnZlcnQiLCItcXVhbGl0eSA5MCAtcmVzaXplIDUxMng1MTJcdTAwM2UiXV0.jpg?sha=be9b892178f0592e"
    },
    {
        "Artist": "Eleanor Antin",
        "Title": "The Adventures of a Nurse",
        "Year": "1976",
        "ObjectID": "118510",
        "Work": "https://www.moma.org/collection/works/118510",
        "Thumbnail": "https://www.moma.org/media/W1siZiIsIjEzNjAxMSJdLFsicCIsImNvbnZlcnQiLCItcXVhbGl0eSA5MCAtcmVzaXplIDUxMng1MTJcdTAwM2UiXV0.jpg?sha=7b88b21d90b3f76c"
    },
    {
        "Artist": "Richard Anuszkiewicz",
        "Title": "Red, White and Blue from 1776 USA 1976 Bicentennial Prints",
        "Year": "1975 (Published 1976).",
        "ObjectID": "68735",
        "Work": "https://www.moma.org/collection/works/68735",
        "Thumbnail": null
    },
    {
        "Artist": "Shusaku Arakawa",
        "Title": "The Signified or If, no. 1",
        "Year": "1975-76",
        "ObjectID": "73390",
        "Work": "https://www.moma.org/collection/works/73390",
        "Thumbnail": "https://www.moma.org/media/W1siZiIsIjIxMjU2NCJdLFsicCIsImNvbnZlcnQiLCItcXVhbGl0eSA5MCAtcmVzaXplIDUxMng1MTJcdTAwM2UiXV0.jpg?sha=6be803e62b260608"
    },
    {
        "Artist": "Shusaku Arakawa",
        "Title": "The Signified or If, no. 2",
        "Year": "1975-76",
        "ObjectID": "73398",
        "Work": "https://www.moma.org/collection/works/73398",
        "Thumbnail": "https://www.moma.org/media/W1siZiIsIjI2MjQ2NCJdLFsicCIsImNvbnZlcnQiLCItcXVhbGl0eSA5MCAtcmVzaXplIDUxMng1MTJcdTAwM2UiXV0.jpg?sha=9f27d36f2de20f92"
    },
    {
        "Artist": "Shusaku Arakawa",
        "Title": "The Signified or If, no. 4",
        "Year": "1975-76",
        "ObjectID": "73405",
        "Work": "https://www.moma.org/collection/works/73405",
        "Thumbnail": null
    },
    {
        "Artist": "Shusaku Arakawa",
        "Title": "The Signified or If, no. 5",
        "Year": "1975-76",
        "ObjectID": "73412",
        "Work": "https://www.moma.org/collection/works/73412",
        "Thumbnail": "https://www.moma.org/media/W1siZiIsIjIxMzc4MSJdLFsicCIsImNvbnZlcnQiLCItcXVhbGl0eSA5MCAtcmVzaXplIDUxMng1MTJcdTAwM2UiXV0.jpg?sha=8656cfe75dd9ad77"
    },
    {
        "Artist": "Nobuyoshi Araki",
        "Title": "Untitled from \"My Love, Yoko\"",
        "Year": "1976",
        "ObjectID": "128439",
        "Work": "https://www.moma.org/collection/works/128439",
        "Thumbnail": "https://www.moma.org/media/W1siZiIsIjI1MTIxMiJdLFsicCIsImNvbnZlcnQiLCItcXVhbGl0eSA5MCAtcmVzaXplIDUxMng1MTJcdTAwM2UiXV0.jpg?sha=53349fa3d9631227"
    },
    {
        "Artist": "Arman",
        "Title": "Untitled from Romantic Suite",
        "Year": "1976",
        "ObjectID": "59577",
        "Work": "https://www.moma.org/collection/works/59577",
        "Thumbnail": "https://www.moma.org/media/W1siZiIsIjY3MTg2Il0sWyJwIiwiY29udmVydCIsIi1xdWFsaXR5IDkwIC1yZXNpemUgNTEyeDUxMlx1MDAzZSJdXQ.jpg?sha=6ce53ac5deef44ef"
    },
    {
        "Artist": "Arman",
        "Title": "The Open Mouths (Les Bouches ouvertes)",
        "Year": "1976",
        "ObjectID": "59726",
        "Work": "https://www.moma.org/collection/works/59726",
        "Thumbnail": "https://www.moma.org/media/W1siZiIsIjIxNDMyMiJdLFsicCIsImNvbnZlcnQiLCItcXVhbGl0eSA5MCAtcmVzaXplIDUxMng1MTJcdTAwM2UiXV0.jpg?sha=68453d77382c543b"
    },
    {
        "Artist": "Arman",
        "Title": "Untitled from Romantic Suite",
        "Year": "1976",
        "ObjectID": "69599",
        "Work": "https://www.moma.org/collection/works/69599",
        "Thumbnail": "https://www.moma.org/media/W1siZiIsIjIxMzY4MCJdLFsicCIsImNvbnZlcnQiLCItcXVhbGl0eSA5MCAtcmVzaXplIDUxMng1MTJcdTAwM2UiXV0.jpg?sha=b500e988a4ddadcd"
    },
    {
        "Artist": "Arman",
        "Title": "Constellation Number 18",
        "Year": "1976",
        "ObjectID": "81009",
        "Work": "https://www.moma.org/collection/works/81009",
        "Thumbnail": "https://www.moma.org/media/W1siZiIsIjIwODI5MSJdLFsicCIsImNvbnZlcnQiLCItcXVhbGl0eSA5MCAtcmVzaXplIDUxMng1MTJcdTAwM2UiXV0.jpg?sha=4b965795f0cde8b6"
    },
    {
        "Artist": "Bill Arnold",
        "Title": "Honey Walking Path",
        "Year": "c. 1971",
        "ObjectID": "46023",
        "Work": "https://www.moma.org/collection/works/46023",
        "Thumbnail": "https://www.moma.org/media/W1siZiIsIjI1ODcxOCJdLFsicCIsImNvbnZlcnQiLCItcXVhbGl0eSA5MCAtcmVzaXplIDUxMng1MTJcdTAwM2UiXV0.jpg?sha=8047f1b89e751a08"
    },
    {
        "Artist": "Bill Arnold",
        "Title": "Honey with Stick",
        "Year": "c. 1971",
        "ObjectID": "46098",
        "Work": "https://www.moma.org/collection/works/46098",
        "Thumbnail": "https://www.moma.org/media/W1siZiIsIjI1OTY2OSJdLFsicCIsImNvbnZlcnQiLCItcXVhbGl0eSA5MCAtcmVzaXplIDUxMng1MTJcdTAwM2UiXV0.jpg?sha=1d2b76383d6b9cd4"
    },
    {
        "Artist": "Bill Arnold",
        "Title": "Steve Rubbing Honey on Rug",
        "Year": "c. 1971",
        "ObjectID": "46134",
        "Work": "https://www.moma.org/collection/works/46134",
        "Thumbnail": "https://www.moma.org/media/W1siZiIsIjI1OTM2NiJdLFsicCIsImNvbnZlcnQiLCItcXVhbGl0eSA5MCAtcmVzaXplIDUxMng1MTJcdTAwM2UiXV0.jpg?sha=cca5fcadce1d08ba"
    },
    {
        "Artist": "Bill Arnold",
        "Title": "Honey in Ivy",
        "Year": "c. 1971",
        "ObjectID": "46158",
        "Work": "https://www.moma.org/collection/works/46158",
        "Thumbnail": "https://www.moma.org/media/W1siZiIsIjI1OTM2OCJdLFsicCIsImNvbnZlcnQiLCItcXVhbGl0eSA5MCAtcmVzaXplIDUxMng1MTJcdTAwM2UiXV0.jpg?sha=8a6e30d437fbe95c"
    },
    {
        "Artist": "Bill Arnold",
        "Title": "Honey on Rug",
        "Year": "c. 1971",
        "ObjectID": "46180",
        "Work": "https://www.moma.org/collection/works/46180",
        "Thumbnail": "https://www.moma.org/media/W1siZiIsIjI1OTM3NCJdLFsicCIsImNvbnZlcnQiLCItcXVhbGl0eSA5MCAtcmVzaXplIDUxMng1MTJcdTAwM2UiXV0.jpg?sha=6d546b0d9974337f"
    },
    {
        "Artist": "Bill Arnold",
        "Title": "Honey in Field (large)",
        "Year": "c. 1971",
        "ObjectID": "46203",
        "Work": "https://www.moma.org/collection/works/46203",
        "Thumbnail": "https://www.moma.org/media/W1siZiIsIjI1OTM3NyJdLFsicCIsImNvbnZlcnQiLCItcXVhbGl0eSA5MCAtcmVzaXplIDUxMng1MTJcdTAwM2UiXV0.jpg?sha=1e254b57dd35c282"
    }
]